Workbook

Sheet блок-схема
B2: Алгоритм расчета совокупной стоимости владения и оценки эффективности ИТ-проекта
A37: *- указан № таблицы как в Приложении
A39: **- чистый денежный поток (ЧДП)

Sheet А1.1.1
D1: Таблица А 1.1.1
A3: Справочник статей расходов (условно-прямых), связанных с разработкой ИТ-проекта
A5: Статья затрат | B5: Обозна- чение | C5: Метод расчета | D5: Примечание
A6: 1. Условно-прямые расходы, руб. | B6: РПр_Р | D6: Учитываются расходы, непосредственно относящиеся только к рассматриваемой системе
A7: 1.1. Расходы на оборудование, руб. | B7: РОб
A8: 1.1.1. Расходы на закупку оборудования, руб. | B8: РОб 1 | C8: Прямой счет фактических расходов (цена, доставка, монтаж, системное ПО) | D8: В случае закупки в период разработки системы
A9: 1.1.2. Сумма амортизации капитальных вложений в оборудование, руб. | B9: РОб 2 | C9: где ТП/И - срок полезного использования оборудования, месяцев (ТП/И устанавливается исходя из информации о том, сколько будет использоваться данный объект до его полной замены или модернизации. Если ТП/И меньше жизненного цикла системы, то на соответствующий год в расчете должны быть заложены расходы на закупку оборудования для замены или модернизации) | D9: В случае использования оборудования, ранее закупленного
A10: 1.1.3. Расходы на комплектующие, руб. | B10: РОб 3 | C10: Прямой счет фактических расходов или с помощью нормативного коэффициента к стоимости оборудования
A11: 1.1.4. Расходы на эксплуатацию оборудования, предназначенного для разработки системы, руб. | B11: РОб 4 | C11: где РРасх - стоимость расходных материалов, руб.; Кэи - Коэффициент использования электроустановок (принимается равным 0,9); WОб - суммарная установочная мощность оборудования, КВт.; Fоб - фонд времени работы оборудования, часы, ЦЭл - цена одного КВт-часа э/энергии, руб.
A12: 1.1.5. Стоимость обслуживания оборудования, предназначенного для разработки системы по договору, руб. | B12: РОб 5 | C12: Стоимость по договору обслуживания, руб. | D12: В случае наличия такого договора
A13: 1.1.6. Стоимость аренды оборудования предназначенного для разработки системы, руб. | B13: РОб 6 | C13: Стоимость по договору аренды, руб. | D13: В случае наличия такого договора
A14: 1.2. Расходы на программное обеспечение (ПО), руб. | B14: РПО
A15: 1.2.1. Расходы на закупку ПО, руб. | B15: РПО 1 | C15: Прямой счет фактических расходов (цена, доставка и т.д.) | D15: В случае закупки в период жизненного цикла
A16: 1.2.2. Сумма ежегодного списания затрат на ПО (аналог амортизации), руб. | B16: РПО 2 | C16: где ТП/И - срок полезного использования ПО, месяцев (ТП/И устанавливается исходя из информации о том, сколько будет использоваться данное программное обеспечение до его полной замены. Если ТП/И меньше жизненного цикла подсистемы (задачи), то на соответствующий год в расчете должны быть заложены расходы на закупку нового программного обеспечения для замены) | D16: В случае использования ПО, ранее закупленного
A17: 1.2.3. Затраты на аренду ПО, руб. | B17: РПО 3 | C17: Стоимость по договору аренды | D17: В случае наличия такого договора
A18: 1.2.4. Стоимость актуализации, поддержки и сопровождения ПО, руб. | B18: РПО 4 | C18: Стоимость стоимость по договорам обновления ПО, поддержки и сопровождения | D18: В случае наличия таких договоров
A19: 1.3. Административные расходы, руб. | B19: РАдм
A20: 1.3.1. Затраты на обучение разработчиков вопросам информационных технологий и систем, руб. | B20: РАдм 1 | C20: Стоимость услуг по договорам на обучение персонала | D20: В случае наличия таких договоров
A21: 1.3.2. Затраты на решение задач административного характера, порученные другим организациям в порядке аутсорсинга, руб. | B21: РАдм 2 | C21: Стоимость услуг по договорам аутсорсинга | D21: В случае наличия таких договоров
A22: 1.4. Расходы на оплату труда, связанные с разработкой системы руб. | B22: РФОТ
A23: 1.4.1. Расходы на оплату труда сотрудников по стадиям разработки системы (проектирование, разработка, тестирование, документирование), всего в т.ч.: | B23: РФОТ 1
A24: проектирование | B24: РФОТ 1_1 | C24: , где tр - месячная трудоемкость выполнения работ по разработке подсистемы(проектирование), часов ; Чр - среднечасовая ставка проектировщика (с учетом премий, компенсаций), руб.; R - коэффициент, учитывающий отчисления в социальные фонды | D24: Среднечасовая ставка = месячный оклад / 160 часов. Коэффициент R = 1,302.
A25: разработка | B25: РФОТ 1_2 | C25: расчет производится аналогично РФОТ1_1 | D25: в случае необходимости выполнения данной стадии на этапе разработки
A26: тестирование | B26: РФОТ 1_3 | C26: расчет производится аналогично РФОТ1_2
A27: документирование | B27: РФОТ 1_4 | C27: расчет производится аналогично РФОТ1_3
A28: 1.4.2. Расходы на оплату услуг сторонних разработчиков и консультантов по направлениям разработки системы, всего в т.ч.: | B28: РФОТ 2 | D28: В случае наличия таких договоров
A29: проектирование | B29: РФОТ 2_1 | C29: Стоимость по договорам аутсорсинга
A30: разработка | B30: РФОТ 2_2 | C30: Стоимость по договорам аутсорсинга
A31: тестирование | B31: РФОТ 2_3 | C31: Стоимость по договорам аутсорсинга
A32: документирование | B32: РФОТ 2_4 | C32: Стоимость по договорам аутсорсинга
A33: 1.5. Расходы на связь и коммуникации, руб. | B33: РКом
A34: 1.5.1. Расходы на оплату труда персонала поддержки корпоративной сети, выделенных линий и каналов для системы, руб. | B34: РКом 1 | C34: где tк - месячная трудоемкость выполнения работ по поддержке коммуникаций, часов; ЧК - среднечасовая ставка работника службы поддержки корпоративной сети, выделенных линий и каналов (с учетом премий, компенсаций), руб.; R - коэффициент, учитывающий отчисления в социальные фонды | D34: при наличии такого персонала. Среднечасовая ставка = месячный оклад / 160 часов. Коэффициент R = 1,302.
A35: 1.5.2. Расходы на аренду выделенных линий и каналов на этапе разработки системы, руб. | B35: РКом 2 | C35: Стоимость услуг по договорам аренды | D35: В случае наличия таких договоров
A36: 1.5.3. Расходы на удаленный доступ на этапе разработки системы, руб. | B36: РКом 3 | C36: Стоимость услуг по договорам обеспечения удаленного доступа | D36: В случае наличия таких договоров
A37: 1.5.4. Стоимость поддержки и развития корпоративных сетей передачи данных на этапе разработки системы, руб. | B37: РКом 4 | C37: Стоимость услуг по договорам поддержки корпоративных сетей передачи данных | D37: В случае наличия таких договоров

Sheet А1.2.1
D1: Таблица А 1.2.1
A3: Справочник статей расходов (условно-прямых), связанных с эксплуатацией ИТ-проекта
A5: Статья затрат | B5: Обозна- чение | C5: Метод расчета | D5: Примечание
A6: 1. Условно-прямые расходы, руб. | B6: РПр_Э | D6: Учитываются расходы, непосредственно относящиеся только к рассматриваемой системе
A7: 1.1. Расходы на оборудование, руб. | B7: РОб
A8: 1.1.1. Расходы на закупку оборудования, руб. | B8: РОб 1 | C8: Прямой счет фактических расходов (цена, доставка, монтаж, системное ПО) | D8: В случае закупки в период жизненного цикла
A9: 1.1.2. Сумма амортизации капитальных вложений в оборудование, руб. | B9: РОб 2 | C9: где ТП/И - срок полезного использования оборудования (ТП/И устанавливается исходя из информации о том, сколько будет использоваться данный объект до его полной замены или модернизации. Если ТП/И меньше жизненного цикла системы, то на соответствующий год в расчете должны быть заложены расходы на закупку оборудования для замены или модернизации) | D9: В случае использования оборудования, ранее закупленного
A10: 1.1.3. Расходы на комплектующие, руб. | B10: РОб 3 | C10: Прямой счет фактических расходов или с помощью нормативного коэффициента к стоимости оборудования
A11: 1.1.4. Расходы на эксплуатацию оборудования,связанного с эксплуатацией системы руб. | B11: РОб 4 | C11: где РРасх - стоимость расходных материалов, руб.; Кэи - Коэффициент использования электроустановок (принимается равным 0,9); WОб - суммарная установочная мощность оборудования, КВт.; Fоб - фонд времени работы оборудования, часы, ЦЭл - цена одного КВт-часа э/энергии, руб.
A12: 1.1.5. Стоимость обслуживания оборудования связанного с эксплуатацией системы по договору, руб. | B12: РОб 5 | C12: Стоимость по договору обслуживания | D12: В случае наличия такого договора
A13: 1.1.6. Стоимость аренды оборудования связанного с эксплуатацией системы, руб. | B13: РОб 6 | C13: Стоимость по договору аренды | D13: В случае наличия такого договора
A14: 1.2. Расходы на программное обеспечение (ПО), руб. | B14: РПО
A15: 1.2.1. Расходы на закупку ПО, руб. | B15: РПО 1 | C15: Прямой счет фактических расходов (цена, доставка, монтаж, системное ПО) | D15: В случае закупки в период жизненного цикла
A16: 1.2.2. Сумма ежегодного списания затрат на ПО (аналог амортизации), руб. | B16: РПО 2 | C16: где ТП/И - срок полезного использования ПО (ТП/И устанавливается исходя из информации о том, сколько будет использоваться данное программное обеспечение до его полной замены. Если ТП/И меньше жизненного цикла подсистемы (задачи), то на соответствующий год в расчете должны быть заложены расходы на закупку нового программного обеспечения для замены) | D16: В случае использования ПО, ранее закупленного
A17: 1.2.3. Затраты на аренду ПО, руб. | B17: РПО 3 | C17: Стоимость по договору аренды | D17: В случае наличия такого договора
A18: 1.2.4. Стоимость актуализации, поддержки и сопровождения ПО, руб. | B18: РПО 4 | C18: Стоимость по договорам обновления ПО, поддержки и сопровождения | D18: В случае наличия таких договоров
A19: 1.3. Административные расходы, руб. | B19: РАдм
A20: 1.3.1. Расходы на оплату труда пользователей (операторов) системы, руб. | B20: РАдм 1 | C20: , где tр - месячная трудоемкость выполнения работ, час ; Чр - среднечасовая ставка пользователя (оператора) системы (с учетом премий, компенсаций), руб.; R - коэффициент, учитывающий отчисления в социальные фонды | D20: Рассчитывается отдельно по всем работникам, имеющим разные ставки и роли. Среднечасовая ставка = месячный оклад / 160 часов. Коэффициент R = 1,302.
A21: 1.3.2. Расходы на консультационные услуги третьих фирм и аналогичные платежи, руб. | B21: РАдм 2 | C21: Стоимость работ и услуг по договорам на консультации, прочие услуги и работы, связанные с эксплуатацией подсистемы или задачи | D21: В случае наличия таких договоров
A22: 1.3.3. Расходы на решение задач, порученных другим организациям в порядке аутсорсинга, руб. | B22: РАдм 3 | C22: Стоимость услуг по договорам аутсорсинга | D22: В случае наличия таких договоров
A23: 1.3.4. Затраты на обучение персонала вопросам информационных технологий и систем, руб. | B23: РАдм 4 | C23: Стоимость услуг по договорам на обучение персонала | D23: В случае наличия таких договоров
A24: 1.4. Расходы на оплату труда, связанные с сопровождением и развитием системы, руб. | B24: РФОТ
A25: 1.4.1. Расходы на оплату труда сотрудников по сопровождению и развитию введенной в эксплуатацию системы по направлениям, руб. | B25: РФОТ 1
A26: сопровождение | B26: РФОТ 1_1 | C26: где tс - месячная трудоемкость выполнения работ по сопровождению подсистемы (задачи), час.; Чс - среднечасовая ставка работника службы сопровождения/развития (с учетом премий, компенсаций), руб.; К - коэффициент, учитывающий отчисления в социальные фонды | D26: Среднечасовая ставка = месячный оклад / 160 часов. Коэффициент R = 1,302.
A27: развитие | B27: РФОТ 1_2 | C27: расчет производится аналогично РФОТ1_1
A28: 1.4.2. Расходы на оплату услуг сторонних консультантов и сервисных организаций в части развития и сопровождения системы по направлениям, Всего в т.ч. | B28: РФОТ 2
A29: сопровождение | B29: РФОТ 2_1 | C29: Стоимость по договорам аутсорсинга | D29: В случае наличия таких договоров
A30: развитие | B30: РФОТ 2_2 | C30: Стоимость по договорам аутсорсинга | D30: В случае наличия таких договоров
A31: 1.5. Расходы на связь и коммуникации, руб. | B31: РКом
A32: 1.5.1. Расходы на оплату труда персонала поддержки корпоративной сети, выделенных линий и каналов для системы, руб. | B32: РКом 1 | C32: где tк - месячная трудоемкость выполнения работ по поддержке коммуникаций, часов; ЧК - среднечасовая ставка работника службы поддержки корпоративной сети, выделенных линий и каналов (с учетом премий, компенсаций), руб.; К - коэффициент, учитывающий оотчисления в социальные фонды | D32: при наличии такого персонала. Среднечасовая ставка = месячный оклад / 160 часов. Коэффициент R = 1,302.
A33: 1.5.2. Расходы на аренду выделенных линий и каналов для системы, руб. | B33: РКом 2 | C33: Стоимость услуг по договорам аренды | D33: В случае наличия таких договоров
A34: 1.5.3. Расходы на удаленный доступ для системы, руб. | B34: РКом 3 | C34: Стоимость услуг по договорам обеспечения удаленного доступа | D34: В случае наличия таких договоров
A35: 1.5.4. Стоимость поддержки и развития корпоративных сетей передачи данных для системы, руб. | B35: РКом 4 | C35: Стоимость услуг по договорам поддержки корпоративных сетей передачи данных | D35: В случае наличия таких договоров

Sheet А1.2.2
D1: Таблица А 1.2.2
A3: Справочник статей расходов (условно-косвенных), связанных с эксплуатацией ИТ-проекта
A5: Статья затрат | B5: Обозна- чение | C5: Метод расчета | D5: Примечание | E5: Поправки
A6: 2. Условно-косвенные расходы по подсистеме (системе), руб. | B6: РКос | D6: При упрощенном расчете рассчитываются только для этапа эксплуатации решения. Учитывается часть расходов на систему информационного менеджмента организации (общесистемных), относящаяся к рассматриваемой подсистеме (задаче)
A7: 2.1. Косвенные расходы на общесистемное оборудование, руб. | B7: РКОб | D7: Часть общих расходов за рассматриваемый год, относящихся к создаваемой системе
A8: 2.1.1. Расходы на закупку общесистемного оборудования в год, руб. | B8: РКОб 1 | C8: Прямой счет фактических расходов (цена, доставка, монтаж, системное ПО) | D8: В случае закупки в период жизненного цикла
A9: 2.1.2. Сумма амортизации капитальных вложений в общесистемное оборудование, руб. | B9: РКОб 2 | C9: где ТП/И - срок полезного использования оборудования (значение выбирается также как для аналогичной статьи условно-прямых расходов) | D9: В случае использования оборудования, ранее закупленного, или если срок полезного использования меньше длительности жизненного цикла системы
A10: 2.1.3. Расходы на общесистемные комплектующие за год, руб. | B10: РКОб 3 | C10: Прямой счет фактических расходов или с помощью нормативного коэффициента к стоимости оборудования
A11: 2.1.4. Расходы на эксплуатацию общесистемного оборудования, руб. | B11: РКОб 4 | C11: где РОРасх - годовая стоимость общесистемных расходных материалов, руб.; Кэи - Коэффициент использования электроустановок (принимается 0,9); Wооб - суммарная установочная мощность общесистемного оборудования, Fооб - годовой фонд времени работы оборудования , ЦЭл - цена одного КВт-часа э/энергии
A12: 2.1.5. Стоимость обслуживания общесистемного оборудования по договору, руб. | B12: РКОб 5 | C12: Стоимость по договору обслуживания | D12: В случае наличия такого договора
A13: 2.1.6. Ежегодная стоимость аренды общесистемного оборудования, руб. | B13: РКОб 6 | C13: Стоимость по договору аренды | D13: В случае наличия такого договора
A14: 2.1.7. Коэффициент участия общесистемного оборудования в системе | B14: РУОб | C14: Доля общесистемных ресурсов, связываемых с рассматриваемой подсистемой. Ррассчитывается следующими способами: 1) отношение прямых расходов на оборудование подсистемы к суммарной величине прямых расходов на оборудование всех подсистем 2) Соотношение объемов занимаемой дисковой памяти на общесистемных ресурсах 3) экспертным путем
A15: 2.2. Косвенные расходы на общесистемное программное обеспечение (ПО), руб. | B15: РКПО
A16: 2.2.1. Расходы на закупку общесистемного ПО за год, руб. | B16: РКПО 1 | C16: Прямой счет фактических расходов (цена, доставка, установка) | D16: В случае закупки в период жизненного цикла
A17: 2.2.2. Сумма ежегодного списания затрат на общесистемное ПО, руб. | B17: РКПО 2 | C17: где ТП/И - срок полезного использования ПО (значение выбирается также как для аналогичной статьи условно-прямых расходов) | D17: В случае использования ПО, ранее закупленного, или если его срок полезного использования меньше длительности жизненного цикла системы
A18: 2.2.3. Затраты на аренду общесистемного ПО, руб. | B18: РКПО 3 | C18: Стоимость по договору аренды | D18: В случае наличия такого договора
A19: 2.2.4. Стоимость актуализации, поддержки и сопровождения общесистемного ПО за год, руб. | B19: РКПО 4 | C19: Стоимость по договорам обновления ПО, поддержки и сопровождения | D19: В случае наличия таких договоров
A20: 2.2.5. Коэффициент участия общесистемного ПО в подсистеме | B20: РУПО | C20: Доля общесистемных ресурсов, связываемых рассматриваемой подсистемой. Рассчитывается как 1) Отношение прямых расходов на ПО подсистемы к суммарной величине прямых расходов на ПО всех подсистем 2) Соотношением объемов занимаемой дисковой памяти на общесистемных ресурсах 3) экспертным путем
A21: 2.3. Косвенные административные расходы, руб. | B21: РКАдм
A22: 2.3.1. Расходы на оплату труда лиц, работающих со всей системой (общесистемный персонал), за год, руб. | B22: РКАдм 1 | C22: где FКАдм - месячный фонд времени работы работников; ЧКАдм - среднечасовая ставка работника (с учетом премий, компенсаций); R- коэффициент, учитывающий отчисления в социальные фонды | D22: Рассчитывается отдельно по всем работникам, имеющим разные ставки и роли
A23: 2.3.2. Расходы на консультационные услуги третьих фирм и аналогичные платежи за год, относящиеся ко всей системе организации, руб. | B23: РКАдм 2 | C23: Стоимость работ и услуг по договорам на консультации, прочие услуги и работы, связанные с эксплуатацией системы | D23: В случае наличия таких договоров
A24: 2.3.3. Расходы на решение задач общесистемного характера, порученных другим организациям в порядке аутсорсинга, руб. | B24: РКАдм 3 | C24: Стоимость услуг по договорам аутсорсинга | D24: В случае наличия таких договоров
A25: 2.3.4. Ежегодные затраты на обучение персонала вопросам информационных технологий и систем информационного менеджмента в целом, руб. | B25: РКАдм 4 | C25: Стоимость услуг по договорам на обучение персонала | D25: В случае наличия таких договоров
A26: 2.3.5. Коэффициент участия общесистемного персонала в подсистеме | B26: РУАдм | C26: Доля общесистемных работ, связываемых с рассматриваемой подсистемой. Рассчитывается следующими методами: 1) Отношение прямых расходов на работы с подсистемой к суммарной величине прямых расходов на работы для всех подсистем. 2) экспертным путем.
A27: 2.4. Косвенные расходы на оплату труда, связанные с сопровождением и развитием системы, руб. | B27: РКФОТ
A28: 2.4.1. Расходы на оплату труда сотрудников по сопровождению и развитию общесистемных ресурсов информационного менеджмента в течение года, руб., Всего в т.ч.: | B28: РКФОТ 1
A29: сопровождение | B29: РКФОТ 1_1 | C29: , где tОс - месячная трудоемкость выполнения работ по сопровождению общесистемных ресурсов; Ккфот - коэффициент, характеризующий долю времени, которую работник тратит на работу с системой,ЧОс - среднечасовая ставка работника службы сопровождения (с учетом премий, компенсаций); R - коэффициент, учитывающий отчисления в социальные фонды | D29: Среднечасовая ставка = месячный оклад / 160 часов. Коэффициент R = 1,302.
A30: развитие | B30: РКФОТ 1_2 | C30: расчет производится аналогично РКФОТ1_1
A31: 2.4.2. Расходы на оплату услуг сторонних консультантов и сервисных организаций в части развития и сопровождения общесистемных ресурсов информационного менеджмента в течение года, Всего в т.ч. | B31: РКФОТ 2
A32: сопровождение | B32: РКФОТ 2_1 | C32: Стоимость по договорам аутсорсинга | D32: В случае наличия таких договоров
A33: развитие | B33: РКФОТ 2_2 | C33: Стоимость по договорам аутсорсинга | D33: В случае наличия таких договоров
A34: 2.4.5. Коэффициент участия общесистемных работ в разработке, развитии и сопровождении подсистемы | B34: КУФОТ | C34: Доля общесистемных работ, связываемых с рассматриваемой системой (рассчитывается как отношение прямых расходов на работы с системой к суммарной величине прямых расходов на работы для всех систем. Также может оцениваться экспертным путем)
A35: 2.5. Косвенные расходы на связь и коммуникации для рассматриваемой подсистемы (системы), руб. | B35: РККом
A36: 2.5.1. Расходы на оплату труда персонала поддержки общей корпоративной сети, выделенных линий и каналов за год, руб. | B36: РККом 1 | C36: где tк - месячная трудоемкость выполнения работ по поддержке коммуникаций, часов; Чк- среднечасовая ставка работника службы поддержки корпоративной сети, выделенных линий и каналов (с учетом премий, компенсаций), руб.; К - коэффициент, учитывающий оотчисления в социальные фонды | D36: при наличии такого персонала.Среднечасовая ставка = месячный оклад / 160 часов. Коэффициент R = 1,302.
A37: 2.5.2. Расходы на аренду выделенных общесистемных линий и каналов за год, руб. | B37: РККом 2 | C37: Стоимость услуг по договорам аренды | D37: В случае наличия таких договоров
A38: 2.5.3. Расходы на удаленный общесистемный доступ за год, руб. | B38: РККом 3 | C38: Стоимость услуг по договорам обеспечения удаленного доступа | D38: В случае наличия таких договоров
A39: 2.5.4. Стоимость поддержки и развития общесистемных корпоративных сетей передачи данных, руб. | B39: РККом 4 | C39: Стоимость услуг по договорам поддержки корпоративных сетей передачи данных | D39: В случае наличия таких договоров
A40: 2.5.5. Коэффициент участия общесистемных работ по коммуникациям в разработке, развитии и сопровождении подсистемы | B40: КУКом | C40: Доля общесистемных работ, связываемых с рассматриваемой подсистемой (рассчитывается как отношение прямых расходов на работы с подсистемой к суммарной величине прямых расходов на работы для всех подсистем. Также может оцениваться экспертным путем)

Sheet А1.2.3
D1: Таблица А 1.2.3
A3: Справочник статей расходов (непредвиденных), связанных с эксплуатацией ИТ-проекта
A5: Статья затрат | B5: Обозна- чение | C5: Метод расчета | D5: Примечание
A6: 3. Непредвиденные расходы, руб. | B6: РНепр | D6: При упрощенном расчете рассчитываются только для этапа эксплуатации решения
A7: 3.1. Расходы на операции конечных пользователей | B7: РПольз
A8: 3.1.1. Сумма оплаты труда, в соответствии с количеством часов, затраченных на самообучение сотрудников | B8: РПольз 1 | C8: где tП - суммарные месячные затраты времени сотрудников на самообучение, час.; ЧП- среднечасовая ставка работника (с учетом премий, компенсаций), руб.; R - коэффициент, учитывающий отчисления в социальные фонды | D8: Среднечасовая ставка = месячный оклад / 160 часов. Коэффициент R = 1,302.
A9: 3.1.2. Сумма оплаты труда, соответствующая количеству часов на обслуживание файлов, компьютера и программ | B9: РПольз 2 | C9: где tФ - суммарные месячные затраты времени сотрудников на обслуживание файлов и баз данных, час.; Чп - среднечасовая ставка работника (с учетом премий, компенсаций), руб.; R - коэффициент, учитывающий отчисления в социальные фонды | D9: Среднечасовая ставка = месячный оклад / 160 часов. Коэффициент R = 1,302.
A10: 3.2. Расходы на простои | B10: РПрос | D10: Общие расходы за месяц
A11: 3.2.1. Затраты по количеству часов простоя в соответствии с плановыми или внеплановыми остановками в работе | B11: РПрос 1 | C11: где FП - месячный фонд времени работы персонала, работающего с подсистемой (задачей); КПрос 1 - доля времени простоев= 0,0125; NП - численность персонала; Чп - среднечасовая ставка работника (с учетом премий, компенсаций); К- коэффициент отчислений в социальные фонды | D11: Коэффициент простоев КПрос 1 оценивается экспертным путем на основании имеющейся статистики
A12: 3.2.2. Затраты, соответствующие количеству часов потерь в работе пользователя по вине работника или нехватке возможностей системы | B12: РПрос 2 | C12: где FП - месячный фонд времени работы персонала, работающего с подсистемой (задачей);КПрос 2 - доля времени потерь=0,05; NП - численность персонала; Чп - среднечасовая ставка работника (с учетом премий, компенсаций); К - коэффициент отчислений в социальные фонды | D12: Коэффициент потерь КПрос 2 оценивается экспертным путем на основании имеющейся статистики

Sheet А1.3.1
D1: Таблица А 1.3.1
A3: Расчет совокупной стоимости владения для программного решения
A5: Статья затрат | B5: Обозна- чение | C5: Метод расчета | D5: Примечание
A6: ИТОГО | B6: ССВ | C6: ССВ=РПр_Р+РПр_Э+РКос+РНепр
A7: ТСО на одно рабочее место | B7: ссв | D7: Характеризует расходы на одно рабочее место подсистемы (задачи), что дает возможность оценки расходов при изменении масштаба системы

Sheet Б1.1.1
B1: Таблица Б 1.1.1
A2: Исходные данные для расчета затрат и показателей экономической эффективности
A3: Показатель | B3: Значение | D3: часть
A4: Количество автоматизируемых рабочих мест | B4: 5
A5: Срок службы ПК и ноутбуков, месяцев | B5: 36
A6: Стоимость ПК для разработки системы | B6: 75000
A7: Количество ПК для разработки системы | B7: 2
A8: Стоимость ранее закупленных ноутбуков, используемых на этапе разработки | B8: 75000
A9: Количество используемых ноутбуков на этапе разработки | B9: 0
A10: Стоимость аренды облачного сервера в месяц, руб. | B10: 0
A11: Замена программной системы и общесистемного оборудования по истечении срока службы, лет | B11: 5
A12: Фонд времени работы оборудования на этапе разработки системы в месяц, часов | B12: 160
A13: Стоимость расходных материалов (бумага, картриджи, канцтовары) в месяц, руб. | B13: 0
A14: Суммарная мощность электрооборудования, кВт | B14: 0.15
A15: Стоимость 1 кВт/ч электроэнергии, руб. | B15: 5.5
A16: Стоимость аренды ПО в месяц, руб | B16: =168699/12 -> 14058.25
A17: Стоимость ранее закупленного ПО, используемого для разработки | B17: 0
A18: Срок службы ПО, месяцев | B18: 12
A19: Фонд времени работы проектировщика на этапе разработки системы в месяц, часов | B19: 160
A20: Фонд времени работы разработчика на этапе разработки системы в месяц, часов | B20: 160
A21: Фонд времени работы тестировщика на этапе разработки системы в месяц, часов | B21: 160
A22: Фонд времени работы инженера по стандартизации на этапе разработки системы в месяц, часов | B22: 160
A23: Среднечасовая ставка лиц, работающих с системой на этапе ее разработки и проектирования, руб. | B23: =170000/160 -> 1062.5
A24: Стоимость ранее закупленных ПК, используемых на этапе эксплуатации системы (за единицу) | B24: 75000
A25: Количество ранее закупленных ПК, используемых на этапе эксплуатации системы | B25: 0
A26: Среднечасовая ставка лиц, работающих с системой на этапе эксплуатации в части сопровождения и развития , руб. | B26: =170000/160 -> 1062.5
A27: Фонд времени работы инженера по сопровождению на этапе эксплуатации системы в месяц, часов | B27: 20
A28: Фонд времени работы инженера по развитию на этапе эксплуатации системы в месяц, часов | B28: 2
A29: Затраты на повышение квалификации персонала в части ИТ | B29: 0
A30: Количество операторов, работающих с системой на этапе эксплуатации, чел. | B30: 1
A31: Среднечасовая ставка лиц, работающих с системой в период эксплуатации, руб. | B31: =120000/160 -> 750
A32: Среднечасовая ставка персонала поддержки общей корпоративной сети, выделенных линий и каналов , руб. | B32: 0
A33: Фонд времени работы оператора системы в месяц | B33: 2
A34: Среднечасовая ставка общесистемного персонала, руб. | B34: =120000/160 -> 750
A35: Расходы на закупку общесистемного оборудования | B35: 0
A36: Срок службы ранее закупленного общесистемного оборудования | B36: 30
A37: Стоимость ранее закупленного общесистемного оборудования | B37: 26000000
A38: Стоимость обслуживания общесистемного оборудования годовая | B38: 30000
A39: Расходы на закупку общесистемного ПО | B39: 0
A40: Стоимость доступа в Интернет за месяц, руб. | B40: 2400
A41: Коэффициент отчисления в социальные фонды | B41: 1.302
A42: Доля часов простоя в соответствии с плановыми или внеплановыми остановками в работе | B42: 0.0125
A43: Доля простоя по вине пользователя | B43: 0
A44: Инфляция (h), % | B44: 0.055
A45: Среднемесячные затраты времени сотрудников на самообучение | B45: 0
A46: Среднемесячные затраты времени сотрудников на обслуживание файлов и баз данных | B46: 0
A47: Стоимость ранее закупленного ПО, используемого для эксплуатации системы | B47: =168699/12 -> 14058.25
A48: Количество инженеров по сопровождению, работающих на этапе эксплуатации системы, чел. | B48: 1
A49: Количество инженеров по развитию, работающих на этапе эксплуатации системы, чел. | B49: 1
A50: Количество персонала поддержки общей корпоративной сети, выделенных линий и каналов , чел. | B50: 0
A51: Фонд времени персонала поддержки общей корпоративной сети, выделенных линий и каналов в месяц, часов | B51: 0
A52: Количество общесистемного персонала, чел. | B52: 40000
A53: Фонд времени общесистемного персонала в месяц | B53: 160

Sheet В1.1.1
I1: Таблица В.1.1.1
A3: Расчет условно-прямых расходов, связанных с разработкой ИТ-проекта
A5: Статья затрат | C5: Всего | D5: в т.ч. по периодам (месяцам) разработки системы
D6: 1 месяц | E6: 2 месяц | F6: 3 месяц | G6: 4 месяц | H6: 5 месяц | I6: 6 месяц
A7: 1. Условно-прямые расходы, руб. | B7: РПр_Р | C7: =C8+C15+C20+C23+C34 -> 1425333.9 | D7: =D8+D15+D20+D23+D34 -> 475111.3 | E7: =E8+E15+E20+E23+E34 -> 364441.3 | F7: =F8+F15+F20+F23+F34 -> 585781.3 | G7: =G8+G15+G20+G23+G34 -> 0 | H7: =H8+H15+H20+H23+H34 -> 0 | I7: =I8+I15+I20+I23+I34 -> 0
A8: 1.1. Расходы на оборудование, руб. | B8: РОб | C8: =SUM(C9:C14) -> 356.4 | D8: =SUM(D9:D14) -> 118.8 | E8: =SUM(E9:E14) -> 118.8 | F8: =SUM(F9:F14) -> 118.8 | G8: =SUM(G9:G14) -> 0 | H8: =SUM(H9:H14) -> 0 | I8: =SUM(I9:I14) -> 0
A9: 1.1.1. Расходы на закупку оборудования, руб. | B9: РОб 1 | C9: =SUM(D9:I9) -> 0 | D9: ='Б1.1.1'!$B$8/'Б1.1.1'!$B$5*'Б1.1.1'!$D$13 -> 0 | E9: ='Б1.1.1'!$B$8/'Б1.1.1'!$B$5*'Б1.1.1'!$D$13 -> 0 | F9: ='Б1.1.1'!$B$8/'Б1.1.1'!$B$5*'Б1.1.1'!$D$13 -> 0
A10: 1.1.2. Сумма амортизации капитальных вложений в оборудование, руб. | B10: РОб 2 | C10: =SUM(D10:I10) -> 0 | D10: =('Б1.1.1'!$B$8+'Б1.1.1'!$B$24)/'Б1.1.1'!$B$5*'Б1.1.1'!$B$9 -> 0 | E10: =D10 -> 0 | F10: =E10 -> 0
A11: 1.1.3. Расходы на комплектующие, руб | B11: РОб 3 | C11: =SUM(D11:I11) -> 0 | D11: 0 | E11: 0 | F11: 0
A12: 1.1.4. Расходы на эксплуатацию оборудования, предназначенного для разработки системы, руб. | B12: РОб 4 | C12: =SUM(D12:I12) -> 356.4 | D12: ='Б1.1.1'!$B$13+(0.9*'Б1.1.1'!$B$14*'Б1.1.1'!$B$12*'Б1.1.1'!$B$15) -> 118.8 | E12: ='Б1.1.1'!$B$13+(0.9*'Б1.1.1'!$B$14*'Б1.1.1'!$B$12*'Б1.1.1'!$B$15) -> 118.8 | F12: ='Б1.1.1'!$B$13+(0.9*'Б1.1.1'!$B$14*'Б1.1.1'!$B$12*'Б1.1.1'!$B$15) -> 118.8
A13: 1.1.5. Стоимость обслуживания оборудования, предназначенного для разработки системы по договору, руб. | B13: РОб 5 | C13: =SUM(D13:I13) -> 0 | D13: 0 | E13: 0 | F13: 0
A14: 1.1.6. Стоимость аренды оборудования предназначенного для разработки системы, руб. | B14: РОб 6 | C14: =SUM(D14:I14) -> 0 | D14: ='Б1.1.1'!$B$10 -> 0 | E14: ='Б1.1.1'!$B$10 -> 0 | F14: ='Б1.1.1'!$B$10 -> 0
A15: 1.2. Расходы на программное обеспечение (ПО), руб. | B15: РПО | C15: =SUM(C16:C19) -> 421747.5 | D15: =SUM(D16:D19) -> 140582.5 | E15: =SUM(E16:E19) -> 140582.5 | F15: =SUM(F16:F19) -> 140582.5 | G15: =SUM(G16:G19) -> 0 | H15: =SUM(H16:H19) -> 0 | I15: =SUM(I16:I19) -> 0
A16: 1.2.1. Расходы на закупку ПО, руб. | B16: РПО 1 | C16: =SUM(D16:I16) -> 421747.5 | D16: =('Б1.1.1'!$B$39*'Б1.1.1'!$B$4)+('Б1.1.1'!$B$47*'Б1.1.1'!$B$4)+('Б1.1.1'!$B$16*'Б1.1.1'!$B$4)+('Б1.1.1'!$B$17*'Б1.1.1'!$B$4) -> 140582.5 | E16: =('Б1.1.1'!B39*'Б1.1.1'!B4)+('Б1.1.1'!B47*'Б1.1.1'!B4)+('Б1.1.1'!B16*'Б1.1.1'!B4)+('Б1.1.1'!B17*'Б1.1.1'!B4) -> 140582.5 | F16: =('Б1.1.1'!B39*'Б1.1.1'!B4)+('Б1.1.1'!B47*'Б1.1.1'!B4)+('Б1.1.1'!B16*'Б1.1.1'!B4)+('Б1.1.1'!B17*'Б1.1.1'!B4) -> 140582.5
A17: 1.2.2. Сумма ежегодного списания затрат на ПО (аналог амортизации), руб. | B17: РПО 2 | C17: =SUM(D17:I17) -> 0 | D17: ='Б1.1.1'!$B$17/'Б1.1.1'!$B$18 -> 0 | E17: ='Б1.1.1'!$B$17/'Б1.1.1'!$B$18 -> 0 | F17: ='Б1.1.1'!$B$17/'Б1.1.1'!$B$18 -> 0 | K17: Срок полезного использования ПО 10 лет, если другое не установлено в договором
A18: 1.2.3. Затраты на аренду ПО, руб. | B18: РПО 3 | C18: =SUM(D18:I18) -> 0 | D18: 0 | E18: 0 | F18: 0
A19: 1.2.4. Стоимость актуализации, поддержки и сопровождения ПО, руб. | B19: РПО 4 | C19: =SUM(D19:I19) -> 0 | D19: 0 | E19: 0 | F19: 0
A20: 1.3. Административные расходы, руб. | B20: РАдм | C20: =SUM(C21:C22) -> 0 | D20: =SUM(D21:D22) -> 0 | E20: =SUM(E21:E22) -> 0 | F20: =SUM(F21:F22) -> 0 | G20: =SUM(G21:G22) -> 0 | H20: =SUM(H21:H22) -> 0 | I20: =SUM(I21:I22) -> 0
A21: 1.3.1. Затраты на обучение разработчиков вопросам информационных технологий и систем, руб. | B21: РАдм 1 | C21: =SUM(D21:I21) -> 0 | D21: 0 | E21: 0 | F21: 0 | G21: 0 | H21: 0 | I21: 0
A22: 1.3.2. Затраты на решение задач административного характера, порученные другим организациям в порядке аутсорсинга, руб. | B22: РАдм 2 | C22: =SUM(D22:I22) -> 0 | D22: 0 | E22: 0 | F22: 0 | G22: 0 | H22: 0 | I22: 0
A23: 1.4. Расходы на оплату труда, связанные с разработке системы руб. | B23: РФОТ | C23: =C24+C29 -> 996030 | D23: =D24+D29 -> 332010 | E23: =E24+E29 -> 221340 | F23: =F24+F29 -> 442680 | G23: =G24+G29 -> 0 | H23: =H24+H29 -> 0 | I23: =I24+I29 -> 0
A24: 1.4.1. Расходы на оплату труда сотрудников по стадиям разработки системы (проектирование, разработка, тестирование, документирование), всего в т.ч.: | B24: РФОТ 1 | C24: =SUM(C25:C28) -> 996030 | D24: =D25+D26+D27+D28 -> 332010 | E24: =E25+E26+E27+E28 -> 221340 | F24: =F25+F26+F27+F28 -> 442680 | G24: =G25+G26+G27+G28 -> 0 | H24: =H25+H26+H27+H28 -> 0 | I24: =I25+I26+I27+I28 -> 0
A25: проектирование | B25: РФОТ 1_1 | C25: =SUM(D25:I25) -> 221340 | D25: ='Б1.1.1'!B23*'Б1.1.1'!B19*'Б1.1.1'!B41 -> 221340 | E25: 0 | F25: 0
A26: разработка | B26: РФОТ 1_2 | C26: =SUM(D26:I26) -> 332010 | D26: ='Б1.1.1'!B23*'Б1.1.1'!B20*'Б1.1.1'!B41/2 -> 110670 | E26: ='Б1.1.1'!B23*'Б1.1.1'!B20*'Б1.1.1'!B41 -> 221340 | F26: 0
A27: тестирование | B27: РФОТ 1_3 | C27: =SUM(D27:I27) -> 221340 | D27: 0 | E27: 0 | F27: ='Б1.1.1'!B23*'Б1.1.1'!B21*'Б1.1.1'!B41 -> 221340
A28: документирование | B28: РФОТ 1_4 | C28: =SUM(D28:I28) -> 221340 | D28: 0 | E28: 0 | F28: ='Б1.1.1'!B23*'Б1.1.1'!B22*'Б1.1.1'!B41 -> 221340
A29: 1.4.2. Расходы на оплату услуг сторонних разработчиков и консультантов по направлениям разработки системы, всего в т.ч.: | B29: РФОТ 2 | C29: =SUM(C30:C33) -> 0 | D29: =D30+D31+D32+D33 -> 0 | E29: =E30+E31+E32+E33 -> 0 | F29: =F30+F31+F32+F33 -> 0 | G29: =G30+G31+G32+G33 -> 0 | H29: =H30+H31+H32+H33 -> 0 | I29: =I30+I31+I32+I33 -> 0
A30: проектирование | B30: РФОТ 2_1 | C30: =SUM(D30:H31) -> 0 | D30: 0 | E30: 0 | F30: 0 | G30: 0 | H30: 0 | I30: 0
A31: разработка | B31: РФОТ 2_2 | C31: =SUM(D31:H32) -> 0 | D31: 0 | E31: 0 | F31: 0 | G31: 0 | H31: 0 | I31: 0
A32: тестирование | B32: РФОТ 2_3 | C32: =SUM(D32:H33) -> 0 | D32: 0 | E32: 0 | F32: 0 | G32: 0 | H32: 0 | I32: 0
A33: документирование | B33: РФОТ 2_4 | C33: =SUM(D33:H33) -> 0 | D33: 0 | E33: 0 | F33: 0 | G33: 0 | H33: 0 | I33: 0
A34: 1.5. Расходы на связь и коммуникации, руб. | B34: РКом | C34: =SUM(C35:C38) -> 7200 | D34: =SUM(D35:D38) -> 2400 | E34: =SUM(E35:E38) -> 2400 | F34: =SUM(F35:F38) -> 2400 | G34: =SUM(G35:G38) -> 0 | H34: =SUM(H35:H38) -> 0 | I34: =SUM(I35:I38) -> 0
A35: 1.5.1. Расходы на оплату труда персонала поддержки корпоративной сети, выделенных линий и каналов для системы, руб. | B35: РКом 1 | C35: =SUM(D35:I35) -> 0 | D35: 0 | E35: 0 | F35: 0
A36: 1.5.2. Расходы на аренду выделенных линий и каналов на этапе разработки системы, руб. | B36: РКом 2 | C36: =SUM(D36:I36) -> 0 | D36: 0 | E36: 0 | F36: 0
A37: 1.5.3. Расходы на удаленный доступ на этапе разработки системы, руб. | B37: РКом 3 | C37: =SUM(D37:I37) -> 7200 | D37: ='Б1.1.1'!$B$40 -> 2400 | E37: ='Б1.1.1'!$B$40 -> 2400 | F37: ='Б1.1.1'!$B$40 -> 2400
A38: 1.5.4. Стоимость поддержки и развития корпоративных сетей передачи данных на этапе разработки системы, руб. | B38: РКом 4 | C38: =SUM(D38:I38) -> 0 | D38: 0 | E38: 0 | F38: 0

Sheet В1.2.1
S1: Таблица В 1.2.1
A3: Расчет расходов (условно-прямых), связанных с эксплуатацией ИТ-проекта
A5: Статья затрат | B5: Обозна- чение | C5: Всего | D5: в т.ч. по периодам эксплуатации системы
D6: 1 год, всего | E6: в т.ч. по периодам (месяцам) 1-го года жизни решения | Q6: 2 | R6: 3 | S6: 4 | T6: 5
E7: 1 месяц (разработка) | F7: 2 месяц (разработка) | G7: 3 месяц (разработка) | H7: 4 месяц | I7: 5 месяц | J7: 6 месяц | K7: 7 месяц | L7: 8 месяц | M7: 9 месяц | N7: 10 месяц | O7: 11 месяц | P7: 12 месяц | R7: 3
A8: 1. Условно-прямые расходы, руб. | B8: РПр_Э | C8: =C9+C16+C21+C33+C26 -> 1046570.9 | D8: =D9+D16+D21+D33+D26 -> 285428.44 | E8: =E9+E16+E21+E33+E26 -> 0 | F8: =F9+F16+F21+F33+F26 -> 0 | G8: =G9+G16+G21+G33+G26 -> 0 | H8: =H9+H16+H21+H33+H26 -> 30792.021 | I8: =I9+I16+I21+I33+I26 -> 30792.021 | J8: =J9+J16+J21+J33+J26 -> 33558.771 | ... T8: =T9+T16+T21+T33+T26 -> 0
A9: 1.1. Расходы на оборудование, руб. | B9: РОб | C9: =SUM(C10:C15) -> 0 | D9: =SUM(D10:D15) -> 0 | E9: =SUM(E10:E15) -> 0 | F9: =SUM(F10:F15) -> 0 | G9: =SUM(G10:G15) -> 0 | H9: =SUM(H10:H15) -> 0 | I9: =SUM(I10:I15) -> 0 | J9: =SUM(J10:J15) -> 0 | ... T9: =SUM(T10:T15) -> 0
A10: 1.1.1. Расходы на закупку оборудования, руб. | B10: РОб 1 | C10: =D10+Q10+R10+S10+T10 -> 0 | D10: =SUM(E10:P10) -> 0 | H10: 0 | I10: 0 | J10: 0 | K10: 0 | L10: 0 | M10: 0 | N10: 0 | O10: 0 | P10: 0 | Q10: 0 | R10: 0
A11: 1.1.2. Сумма амортизации капитальных вложений в оборудование, руб. | B11: РОб 2 | C11: =D11+Q11+R11+S11+T11 -> 0 | D11: =SUM(E11:P11) -> 0 | E11: 0 | F11: 0 | G11: 0 | H11: =('Б1.1.1'!$B$24*'Б1.1.1'!$B$25)/'Б1.1.1'!$B$5 -> 0 | I11: =('Б1.1.1'!$B$24*'Б1.1.1'!$B$25)/'Б1.1.1'!$B$5 -> 0 | J11: =('Б1.1.1'!$B$24*'Б1.1.1'!$B$25)/'Б1.1.1'!$B$5 -> 0 | K11: =('Б1.1.1'!$B$24*'Б1.1.1'!$B$25)/'Б1.1.1'!$B$5 -> 0 | L11: =('Б1.1.1'!$B$24*'Б1.1.1'!$B$25)/'Б1.1.1'!$B$5 -> 0 | M11: =('Б1.1.1'!$B$24*'Б1.1.1'!$B$25)/'Б1.1.1'!$B$5 -> 0 | N11: =('Б1.1.1'!$B$24*'Б1.1.1'!$B$25)/'Б1.1.1'!$B$5 -> 0 | O11: =('Б1.1.1'!$B$24*'Б1.1.1'!$B$25)/'Б1.1.1'!$B$5 -> 0 | P11: =('Б1.1.1'!$B$24*'Б1.1.1'!$B$25)/'Б1.1.1'!$B$5 -> 0 | Q11: =P11*12 -> 0 | R11: =P11*12 -> 0
A12: 1.1.3. Расходы на комплектующие, руб | B12: РОб 3 | C12: =D12+Q12+R12+S12+T12 -> 0 | D12: =SUM(E12:P12) -> 0 | H12: 0 | I12: 0 | J12: 0 | K12: 0 | L12: 0 | M12: 0 | N12: 0 | O12: 0 | P12: 0 | Q12: 0 | R12: 0
A13: 1.1.4. Расходы на эксплуатацию оборудования, руб. | B13: РОб 4 | C13: =D13+Q13+R13+S13+T13 -> 0 | D13: =SUM(E13:P13) -> 0 | H13: 0 | I13: 0 | J13: 0 | K13: 0 | L13: 0 | M13: 0 | N13: 0 | O13: 0 | P13: 0 | Q13: 0 | R13: 0
A14: 1.1.5. Стоимость обслуживания оборудования по договору, руб. | B14: РОб 5 | C14: =D14+Q14+R14+S14+T14 -> 0 | D14: =SUM(E14:P14) -> 0 | H14: 0 | I14: 0 | J14: 0 | K14: 0 | L14: 0 | M14: 0 | N14: 0 | O14: 0 | P14: 0 | Q14: 0 | R14: 0
A15: 1.1.6. Стоимость аренды оборудования, руб. | B15: РОб 6 | C15: =D15+Q15+R15+S15+T15 -> 0 | D15: =SUM(E15:P15) -> 0 | H15: 0 | I15: 0 | J15: 0 | K15: 0 | L15: 0 | M15: 0 | N15: 0 | O15: 0 | P15: 0 | Q15: 0 | R15: 0
A16: 1.2. Расходы на программное обеспечение (ПО), руб. | B16: РПО | C16: =D16+Q16+R16+S16+T16 -> 38660.188 | D16: =SUM(D17:D20) -> 10543.688 | E16: =SUM(E17:E20) -> 0 | F16: =SUM(F17:F20) -> 0 | G16: =SUM(G17:G20) -> 0 | H16: =SUM(H17:H20) -> 1171.5208 | I16: =SUM(I17:I20) -> 1171.5208 | J16: =SUM(J17:J20) -> 1171.5208 | K16: =SUM(K17:K20) -> 1171.5208 | ... T16: =SUM(T17:T20) -> 0
A17: 1.2.1. Расходы на закупку ПО, руб. | B17: РПО 1 | C17: =D17+Q17+R17+S17+T17 -> 0 | D17: =SUM(E17:P17) -> 0
A18: 1.2.2. Сумма ежегодного списания затрат на ПО (аналог амортизации), руб. | B18: РПО 2 | C18: =D18+Q18+R18+S18+T18 -> 38660.188 | D18: =SUM(E18:P18) -> 10543.688 | E18: 0 | F18: 0 | G18: 0 | H18: ='Б1.1.1'!$B$47/'Б1.1.1'!$B$18 -> 1171.5208 | I18: ='Б1.1.1'!$B$47/'Б1.1.1'!$B$18 -> 1171.5208 | J18: ='Б1.1.1'!$B$47/'Б1.1.1'!$B$18 -> 1171.5208 | K18: ='Б1.1.1'!$B$47/'Б1.1.1'!$B$18 -> 1171.5208 | L18: ='Б1.1.1'!$B$47/'Б1.1.1'!$B$18 -> 1171.5208 | M18: ='Б1.1.1'!$B$47/'Б1.1.1'!$B$18 -> 1171.5208 | N18: ='Б1.1.1'!$B$47/'Б1.1.1'!$B$18 -> 1171.5208 | O18: ='Б1.1.1'!$B$47/'Б1.1.1'!$B$18 -> 1171.5208 | P18: ='Б1.1.1'!$B$47/'Б1.1.1'!$B$18 -> 1171.5208 | Q18: =P18*12 -> 14058.25 | R18: =P18*12 -> 14058.25
A19: 1.2.3. Затраты на аренду ПО, руб. | B19: РПО 3 | C19: =D19+Q19+R19+S19+T19 -> 0 | D19: =SUM(E19:P19) -> 0
A20: 1.2.4. Стоимость актуализации, поддержки и сопровождения ПО, руб. | B20: РПО 4 | C20: =D20+Q20+R20+S20+T20 -> 0 | D20: =SUM(E20:P20) -> 0
A21: 1.3. Административные расходы, руб. | B21: РАдм | C21: =SUM(C22:C25) -> 64449 | D21: =SUM(D22:D25) -> 17577 | E21: =SUM(E22:E25) -> 0 | F21: =SUM(F22:F25) -> 0 | G21: =SUM(G22:G25) -> 0 | H21: =SUM(H22:H25) -> 1953 | I21: =SUM(I22:I25) -> 1953 | J21: =SUM(J22:J25) -> 1953 | ... T21: =SUM(T22:T25) -> 0
A22: 1.3.1. Расходы на оплату труда пользователей (операторов) системы, руб. | B22: РАдм 1 | C22: =D22+Q22+R22+S22+T22 -> 64449 | D22: =SUM(E22:P22) -> 17577 | H22: ='Б1.1.1'!$B$33*'Б1.1.1'!$B$31*'Б1.1.1'!$B$30*'Б1.1.1'!$B$41 -> 1953 | I22: ='Б1.1.1'!$B$33*'Б1.1.1'!$B$31*'Б1.1.1'!$B$30*'Б1.1.1'!$B$41 -> 1953 | J22: ='Б1.1.1'!$B$33*'Б1.1.1'!$B$31*'Б1.1.1'!$B$30*'Б1.1.1'!$B$41 -> 1953 | K22: ='Б1.1.1'!$B$33*'Б1.1.1'!$B$31*'Б1.1.1'!$B$30*'Б1.1.1'!$B$41 -> 1953 | L22: ='Б1.1.1'!$B$33*'Б1.1.1'!$B$31*'Б1.1.1'!$B$30*'Б1.1.1'!$B$41 -> 1953 | M22: ='Б1.1.1'!$B$33*'Б1.1.1'!$B$31*'Б1.1.1'!$B$30*'Б1.1.1'!$B$41 -> 1953 | N22: ='Б1.1.1'!$B$33*'Б1.1.1'!$B$31*'Б1.1.1'!$B$30*'Б1.1.1'!$B$41 -> 1953 | O22: ='Б1.1.1'!$B$33*'Б1.1.1'!$B$31*'Б1.1.1'!$B$30*'Б1.1.1'!$B$41 -> 1953 | P22: ='Б1.1.1'!$B$33*'Б1.1.1'!$B$31*'Б1.1.1'!$B$30*'Б1.1.1'!$B$41 -> 1953 | Q22: =P22*12 -> 23436 | R22: =P22*12 -> 23436 | U22: второй и последующие годы =ФОТ месяц*12
A23: 1.3.2. Расходы на консультационные услуги третьих фирм и аналогичные платежи, руб. | B23: РАдм 2 | C23: =D23+Q23+R23+S23+T23 -> 0 | D23: =SUM(E23:P23) -> 0
A24: 1.3.3. Расходы на решение задач, порученных другим организациям в порядке аутсорсинга, руб. | B24: РАдм 3 | C24: =D24+Q24+R24+S24+T24 -> 0 | D24: =SUM(E24:P24) -> 0
A25: 1.3.4. Затраты на обучение персонала вопросам информационных технологий и систем, руб. | B25: РАдм 4 | C25: =D25+Q25+R25+S25+T25 -> 0 | D25: =SUM(E25:P25) -> 0
A26: 1.4. Расходы связанные с сопровождением и развитием системы, руб. | B26: РФОТ | C26: =C27+C30 -> 943461.75 | D26: =D27+D30 -> 257307.75 | E26: =E27+E30 -> 0 | F26: =F27+F30 -> 0 | G26: =G27+G30 -> 0 | H26: =H27+H30 -> 27667.5 | I26: =I27+I30 -> 27667.5 | J26: =J27+J30 -> 30434.25 | ... T26: =T27+T30 -> 0
A27: 1.4.1. Расходы на оплату труда сотрудников по сопровождению и развитию введенной в эксплуатацию системы по направлениям, руб. Всего, в т.ч. | B27: РФОТ 1 | C27: =C28+C29 -> 943461.75 | D27: =D28+D29 -> 257307.75 | E27: =E28+E29 -> 0 | F27: =F28+F29 -> 0 | G27: =G28+G29 -> 0 | H27: =H28+H29 -> 27667.5 | I27: =I28+I29 -> 27667.5 | J27: =J28+J29 -> 30434.25 | ... T27: =T28+T29 -> 0
A28: сопровождение | B28: РФОТ 1_1 | C28: =D28+Q28+R28+S28+T28 -> 913027.5 | D28: =SUM(E28:P28) -> 249007.5 | H28: ='Б1.1.1'!$B$26*'Б1.1.1'!$B$27*'Б1.1.1'!$B$48*'Б1.1.1'!$B$41 -> 27667.5 | I28: ='Б1.1.1'!$B$26*'Б1.1.1'!$B$27*'Б1.1.1'!$B$48*'Б1.1.1'!$B$41 -> 27667.5 | J28: ='Б1.1.1'!$B$26*'Б1.1.1'!$B$27*'Б1.1.1'!$B$48*'Б1.1.1'!$B$41 -> 27667.5 | K28: ='Б1.1.1'!$B$26*'Б1.1.1'!$B$27*'Б1.1.1'!$B$48*'Б1.1.1'!$B$41 -> 27667.5 | L28: ='Б1.1.1'!$B$26*'Б1.1.1'!$B$27*'Б1.1.1'!$B$48*'Б1.1.1'!$B$41 -> 27667.5 | M28: ='Б1.1.1'!$B$26*'Б1.1.1'!$B$27*'Б1.1.1'!$B$48*'Б1.1.1'!$B$41 -> 27667.5 | N28: ='Б1.1.1'!$B$26*'Б1.1.1'!$B$27*'Б1.1.1'!$B$48*'Б1.1.1'!$B$41 -> 27667.5 | O28: ='Б1.1.1'!$B$26*'Б1.1.1'!$B$27*'Б1.1.1'!$B$48*'Б1.1.1'!$B$41 -> 27667.5 | P28: ='Б1.1.1'!$B$26*'Б1.1.1'!$B$27*'Б1.1.1'!$B$48*'Б1.1.1'!$B$41 -> 27667.5 | Q28: =P28*12 -> 332010 | R28: =P28*12 -> 332010 | U28: второй и последующие годы =ФОТ месяц*12
A29: развитие | B29: РФОТ 1_2 | C29: =D29+Q29+R29+S29+T29 -> 30434.25 | D29: =SUM(E29:P29) -> 8300.25 | J29: ='Б1.1.1'!$B$28*'Б1.1.1'!$B$26*'Б1.1.1'!$B$49*'Б1.1.1'!$B$41 -> 2766.75 | M29: ='Б1.1.1'!$B$28*'Б1.1.1'!$B$26*'Б1.1.1'!$B$49*'Б1.1.1'!$B$41 -> 2766.75 | P29: ='Б1.1.1'!$B$28*'Б1.1.1'!$B$26*'Б1.1.1'!$B$49*'Б1.1.1'!$B$41 -> 2766.75 | Q29: =P29*4 -> 11067 | R29: =P29*4 -> 11067 | U29: четыре месяца в год
A30: 1.4.4. Расходы на оплату услуг консультантов и сервисных организаций в части развития и сопровождения системы по направлениям, руб. Всего, в т.ч. | B30: РФОТ 2 | C30: =C31+C32 -> 0 | D30: =D31+D32 -> 0 | E30: =E31+E32 -> 0 | F30: =F31+F32 -> 0 | G30: =G31+G32 -> 0 | H30: =H31+H32 -> 0 | I30: =I31+I32 -> 0 | J30: =J31+J32 -> 0 | ... T30: =T31+T32 -> 0
A31: сопровождение | B31: РФОТ 2_1 | C31: =D31+Q31+R31+S31+T31 -> 0 | D31: =SUM(E31:P31) -> 0
A32: развитие | B32: РФОТ 2_2 | C32: =D32+Q32+R32+S32+T32 -> 0 | D32: =SUM(E32:P32) -> 0
A33: 1.5. Расходы на связь и коммуникации, руб. | B33: РКом | C33: =SUM(C34:C37) -> 0 | D33: =SUM(D34:D37) -> 0 | E33: =SUM(E34:E37) -> 0 | F33: =SUM(F34:F37) -> 0 | G33: =SUM(G34:G37) -> 0 | H33: =SUM(H34:H37) -> 0 | I33: =SUM(I34:I37) -> 0 | J33: =SUM(J34:J37) -> 0 | ... T33: =SUM(T34:T37) -> 0
A34: 1.5.1. Расходы на оплату труда персонала поддержки корпоративной сети, выделенных линий и каналов для системы, руб. | B34: РКом 1 | C34: =D34+Q34+R34+S34+T34 -> 0 | D34: =SUM(E34:P34) -> 0 | H34: ='Б1.1.1'!B$32*'Б1.1.1'!B$51*'Б1.1.1'!B$50*'Б1.1.1'!B$41 -> 0 | I34: ='Б1.1.1'!$B$32*'Б1.1.1'!$B$51*'Б1.1.1'!$B$50*'Б1.1.1'!$B$41 -> 0 | J34: ='Б1.1.1'!$B$32*'Б1.1.1'!$B$51*'Б1.1.1'!$B$50*'Б1.1.1'!$B$41 -> 0 | K34: ='Б1.1.1'!$B$32*'Б1.1.1'!$B$51*'Б1.1.1'!$B$50*'Б1.1.1'!$B$41 -> 0 | L34: ='Б1.1.1'!$B$32*'Б1.1.1'!$B$51*'Б1.1.1'!$B$50*'Б1.1.1'!$B$41 -> 0 | M34: ='Б1.1.1'!$B$32*'Б1.1.1'!$B$51*'Б1.1.1'!$B$50*'Б1.1.1'!$B$41 -> 0 | N34: ='Б1.1.1'!$B$32*'Б1.1.1'!$B$51*'Б1.1.1'!$B$50*'Б1.1.1'!$B$41 -> 0 | O34: ='Б1.1.1'!$B$32*'Б1.1.1'!$B$51*'Б1.1.1'!$B$50*'Б1.1.1'!$B$41 -> 0 | P34: ='Б1.1.1'!$B$32*'Б1.1.1'!$B$51*'Б1.1.1'!$B$50*'Б1.1.1'!$B$41 -> 0 | Q34: =P34*12 -> 0 | R34: =P34*12 -> 0
A35: 1.5.2. Расходы на аренду выделенных линий и каналов для системы, руб. | B35: РКом 2 | C35: =D35+Q35+R35+S35+T35 -> 0 | D35: =SUM(E35:P35) -> 0 | H35: ='Б1.1.1'!$B$32*'Б1.1.1'!$B$51*'Б1.1.1'!$B$50*'Б1.1.1'!$B$41 -> 0 | I35: ='Б1.1.1'!$B$32*'Б1.1.1'!$B$51*'Б1.1.1'!$B$50*'Б1.1.1'!$B$41 -> 0 | J35: ='Б1.1.1'!$B$32*'Б1.1.1'!$B$51*'Б1.1.1'!$B$50*'Б1.1.1'!$B$41 -> 0 | K35: ='Б1.1.1'!$B$32*'Б1.1.1'!$B$51*'Б1.1.1'!$B$50*'Б1.1.1'!$B$41 -> 0 | L35: ='Б1.1.1'!$B$32*'Б1.1.1'!$B$51*'Б1.1.1'!$B$50*'Б1.1.1'!$B$41 -> 0 | M35: ='Б1.1.1'!$B$32*'Б1.1.1'!$B$51*'Б1.1.1'!$B$50*'Б1.1.1'!$B$41 -> 0 | N35: ='Б1.1.1'!$B$32*'Б1.1.1'!$B$51*'Б1.1.1'!$B$50*'Б1.1.1'!$B$41 -> 0 | O35: ='Б1.1.1'!$B$32*'Б1.1.1'!$B$51*'Б1.1.1'!$B$50*'Б1.1.1'!$B$41 -> 0 | P35: ='Б1.1.1'!$B$32*'Б1.1.1'!$B$51*'Б1.1.1'!$B$50*'Б1.1.1'!$B$41 -> 0 | Q35: =P35*12 -> 0 | R35: =P35*12 -> 0
A36: 1.5.3. Расходы на удаленный доступ для системы, руб. | B36: РКом 3 | C36: =D36+Q36+R36+S36+T36 -> 0 | D36: =SUM(E36:P36) -> 0 | H36: ='Б1.1.1'!$B$32*'Б1.1.1'!$B$51*'Б1.1.1'!$B$50*'Б1.1.1'!$B$41 -> 0 | I36: ='Б1.1.1'!$B$32*'Б1.1.1'!$B$51*'Б1.1.1'!$B$50*'Б1.1.1'!$B$41 -> 0 | J36: ='Б1.1.1'!$B$32*'Б1.1.1'!$B$51*'Б1.1.1'!$B$50*'Б1.1.1'!$B$41 -> 0 | K36: ='Б1.1.1'!$B$32*'Б1.1.1'!$B$51*'Б1.1.1'!$B$50*'Б1.1.1'!$B$41 -> 0 | L36: ='Б1.1.1'!$B$32*'Б1.1.1'!$B$51*'Б1.1.1'!$B$50*'Б1.1.1'!$B$41 -> 0 | M36: ='Б1.1.1'!$B$32*'Б1.1.1'!$B$51*'Б1.1.1'!$B$50*'Б1.1.1'!$B$41 -> 0 | N36: ='Б1.1.1'!$B$32*'Б1.1.1'!$B$51*'Б1.1.1'!$B$50*'Б1.1.1'!$B$41 -> 0 | O36: ='Б1.1.1'!$B$32*'Б1.1.1'!$B$51*'Б1.1.1'!$B$50*'Б1.1.1'!$B$41 -> 0 | P36: ='Б1.1.1'!$B$32*'Б1.1.1'!$B$51*'Б1.1.1'!$B$50*'Б1.1.1'!$B$41 -> 0 | Q36: =P36*12 -> 0 | R36: =P36*12 -> 0 | U36: второй и последующие годы =месяц*12
A37: 1.5.4. Стоимость поддержки и развития корпоративных сетей передачи данных для системы, руб. | B37: РКом 4 | C37: =D37+Q37+R37+S37+T37 -> 0 | D37: =SUM(E37:P37) -> 0 | H37: ='Б1.1.1'!$B$32*'Б1.1.1'!$B$51*'Б1.1.1'!$B$50*'Б1.1.1'!$B$41 -> 0 | I37: ='Б1.1.1'!$B$32*'Б1.1.1'!$B$51*'Б1.1.1'!$B$50*'Б1.1.1'!$B$41 -> 0 | J37: ='Б1.1.1'!$B$32*'Б1.1.1'!$B$51*'Б1.1.1'!$B$50*'Б1.1.1'!$B$41 -> 0 | K37: ='Б1.1.1'!$B$32*'Б1.1.1'!$B$51*'Б1.1.1'!$B$50*'Б1.1.1'!$B$41 -> 0 | L37: ='Б1.1.1'!$B$32*'Б1.1.1'!$B$51*'Б1.1.1'!$B$50*'Б1.1.1'!$B$41 -> 0 | M37: ='Б1.1.1'!$B$32*'Б1.1.1'!$B$51*'Б1.1.1'!$B$50*'Б1.1.1'!$B$41 -> 0 | N37: ='Б1.1.1'!$B$32*'Б1.1.1'!$B$51*'Б1.1.1'!$B$50*'Б1.1.1'!$B$41 -> 0 | O37: ='Б1.1.1'!$B$32*'Б1.1.1'!$B$51*'Б1.1.1'!$B$50*'Б1.1.1'!$B$41 -> 0 | P37: ='Б1.1.1'!$B$32*'Б1.1.1'!$B$51*'Б1.1.1'!$B$50*'Б1.1.1'!$B$41 -> 0 | Q37: =P37*12 -> 0 | R37: =P37*12 -> 0

Sheet В1.2.2
T1: Таблица В1.2.2
A3: Расчет расходов (условно-косвенных), связанных с эксплуатацией ИТ-проекта
A5: Статья затрат | B5: Обозна- чение | C5: Всего | D5: в т.ч. по периодам эксплуатации системы
D6: 1 год, всего | E6: в т.ч. по периодам (месяцам) 1-го года жизни решения | Q6: 2 | R6: 3 | S6: 4 | T6: 5
E7: 1 месяц (разработка) | F7: 2 месяц (разработка) | G7: 3 месяц (разработка) | H7: 4 месяц | I7: 5 месяц | J7: 6 месяц | K7: 7 месяц | L7: 8 месяц | M7: 9 месяц | N7: 10 месяц | O7: 11 месяц | P7: 12 месяц
A8: 2. Условно-косвенные расходы по подсистеме (системе), руб. | B8: РКос | C8: =D8+Q8+R8+S8+T8 -> 7787837.6 | D8: =D9+D17+D23+D29+D37 -> 2127604.3 | E8: =E9+E17+E23+E29+E37 -> 0 | F8: =F9+F17+F23+F29+F37 -> 0 | G8: =G9+G17+G23+G29+G37 -> 0 | H8: =H9+H17+H23+H29+H37 -> 235093.06 | I8: =I9+I17+I23+I29+I37 -> 235093.06 | J8: =J9+J17+J23+J29+J37 -> 235093.06 | K8: =K9+K17+K23+K29+K37 -> 235093.06 | ... T8: =T9+T17+T23+T29+T37 -> 0
A9: 2.1. Косвенные расходы на общесистемное оборудование, руб. | B9: РКОб | C9: =D9+Q9+R9+S9+T9 -> 7178176.1 | D9: =SUM(D10:D15) -> 1959320.8 | E9: =SUM(E10:E15)*E16 -> 0 | F9: =SUM(F10:F15)*F16 -> 0 | G9: =SUM(G10:G15)*G16 -> 0 | H9: =SUM(H10:H15)*H16 -> 216702.31 | I9: =SUM(I10:I15)*I16 -> 216702.31 | J9: =SUM(J10:J15)*J16 -> 216702.31 | K9: =SUM(K10:K15)*K16 -> 216702.31 | L9: =SUM(L10:L15)*L16 -> 216702.31 | ... T9: =SUM(T10:T15)*T16 -> 0
A10: 2.1.1. Расходы на закупку общесистемного оборудования в год, руб. | B10: РКОб 1 | C10: =D10+Q10*$Q$16+R10*$R$16+S10*$S$16+T10*$T$16 -> 0 | D10: =SUM(E10:P10)*$D$16 -> 0
A11: 2.1.2. Сумма амортизации капитальных вложений в общесистемное оборудование, руб. | B11: РКОб 2 | C11: =D11+Q11*$Q$16+R11*$R$16+S11*$S$16+T11*$T$16 -> 7150000 | D11: =SUM(E11:P11)*$D$16 -> 1950000 | H11: ='Б1.1.1'!$B$37/'Б1.1.1'!$B$5 -> 722222.22 | I11: ='Б1.1.1'!$B$37/'Б1.1.1'!$B$5 -> 722222.22 | J11: ='Б1.1.1'!$B$37/'Б1.1.1'!$B$5 -> 722222.22 | K11: ='Б1.1.1'!$B$37/'Б1.1.1'!$B$5 -> 722222.22 | L11: ='Б1.1.1'!$B$37/'Б1.1.1'!$B$5 -> 722222.22 | M11: ='Б1.1.1'!$B$37/'Б1.1.1'!$B$5 -> 722222.22 | N11: ='Б1.1.1'!$B$37/'Б1.1.1'!$B$5 -> 722222.22 | O11: ='Б1.1.1'!$B$37/'Б1.1.1'!$B$5 -> 722222.22 | P11: ='Б1.1.1'!$B$37/'Б1.1.1'!$B$5 -> 722222.22 | Q11: =P11*12 -> 8666666.7 | R11: =P11*12 -> 8666666.7 | S11: 0 | T11: 0 | U11: второй и последующие годы =месяц*12
A12: 2.1.3. Расходы на общесистемные комплектующие за год, руб. | B12: РКОб 3 | C12: =D12+Q12*$Q$16+R12*$R$16+S12*$S$16+T12*$T$16 -> 0 | D12: =SUM(E12:P12)*$D$16 -> 0 | Q12: =P12*12 -> 0 | R12: =P12*12 -> 0
A13: 2.1.4. Расходы на эксплуатацию общесистемного оборудования, руб. | B13: РКОб 4 | C13: =D13+Q13*$Q$16+R13*$R$16+S13*$S$16+T13*$T$16 -> 1176.12 | D13: =SUM(E13:P13)*$D$16 -> 320.76 | H13: ='Б1.1.1'!$B$13+'Б1.1.1'!$B$14*'Б1.1.1'!$B$15*'Б1.1.1'!$B$12*0.9 -> 118.8 | I13: ='Б1.1.1'!$B$13+'Б1.1.1'!$B$14*'Б1.1.1'!$B$15*'Б1.1.1'!$B$12*0.9 -> 118.8 | J13: ='Б1.1.1'!$B$13+'Б1.1.1'!$B$14*'Б1.1.1'!$B$15*'Б1.1.1'!$B$12*0.9 -> 118.8 | K13: ='Б1.1.1'!$B$13+'Б1.1.1'!$B$14*'Б1.1.1'!$B$15*'Б1.1.1'!$B$12*0.9 -> 118.8 | L13: ='Б1.1.1'!$B$13+'Б1.1.1'!$B$14*'Б1.1.1'!$B$15*'Б1.1.1'!$B$12*0.9 -> 118.8 | M13: ='Б1.1.1'!$B$13+'Б1.1.1'!$B$14*'Б1.1.1'!$B$15*'Б1.1.1'!$B$12*0.9 -> 118.8 | N13: ='Б1.1.1'!$B$13+'Б1.1.1'!$B$14*'Б1.1.1'!$B$15*'Б1.1.1'!$B$12*0.9 -> 118.8 | O13: ='Б1.1.1'!$B$13+'Б1.1.1'!$B$14*'Б1.1.1'!$B$15*'Б1.1.1'!$B$12*0.9 -> 118.8 | P13: ='Б1.1.1'!$B$13+'Б1.1.1'!$B$14*'Б1.1.1'!$B$15*'Б1.1.1'!$B$12*0.9 -> 118.8 | Q13: =P13*12 -> 1425.6 | R13: =P13*12 -> 1425.6
A14: 2.1.5. Ежегодная стоимость обслуживания общесистемного оборудования по договору, руб. | B14: РКОб 5 | C14: =D14+Q14*$Q$16+R14*$R$16+S14*$S$16+T14*$T$16 -> 27000 | D14: =SUM(E14:P14)*$D$16 -> 9000 | P14: ='Б1.1.1'!B38 -> 30000 | Q14: =P14 -> 30000 | R14: =P14 -> 30000
A15: 2.1.6. Ежегодная стоимость аренды общесистемного оборудования, руб. | B15: РКОб 6 | C15: =D15+Q15*$Q$16+R15*$R$16+S15*$S$16+T15*$T$16 -> 0 | D15: =SUM(E15:P15)*$D$16 -> 0
A16: 2.1.7. Коэффициент участия общесистемного оборудования в системе | B16: РУОб | C16: =(D16+Q16+R16+S16+T16)/5 -> 0.3 | D16: =SUM(E16:P16)/12 -> 0.3 | E16: 0.3 | F16: 0.3 | G16: 0.3 | H16: 0.3 | I16: 0.3 | J16: 0.3 | K16: 0.3 | L16: 0.3 | M16: 0.3 | N16: 0.3 | O16: 0.3 | P16: 0.3 | Q16: 0.3 | R16: 0.3 | S16: 0.3 | T16: 0.3
A17: 2.2. Косвенные расходы на общесистемное программное обеспечение (ПО), РУб- | B17: РКПО | C17: =D17+Q17+R17+S17+T17 -> 0 | D17: =SUM(D18:D21) -> 0 | E17: =SUM(E18:E21)*E22 -> 0 | F17: =SUM(F18:F21)*F22 -> 0 | G17: =SUM(G18:G21)*G22 -> 0 | H17: =SUM(H18:H21)*H22 -> 0 | I17: =SUM(I18:I21)*I22 -> 0 | J17: =SUM(J18:J21)*J22 -> 0 | K17: =SUM(K18:K21)*K22 -> 0 | L17: =SUM(L18:L21)*L22 -> 0 | ... T17: =SUM(T18:T21)*T22 -> 0
A18: 2.2.1. Расходы на закупку общесистемного ПО за год, руб. | B18: РКПО 1 | C18: =D18+Q18*$Q$22+R18*$R$22+S18*$S$22+T18*$T$22 -> 0 | D18: =SUM(E18:P18)*$D$22 -> 0 | H18: ='Б1.1.1'!$B$39/'Б1.1.1'!$B$18 -> 0 | I18: ='Б1.1.1'!$B$39/'Б1.1.1'!$B$18 -> 0 | J18: ='Б1.1.1'!$B$39/'Б1.1.1'!$B$18 -> 0 | K18: 0 | L18: 0 | M18: 0 | N18: 0 | O18: 0 | P18: 0 | Q18: 0 | R18: 0 | S18: 0 | T18: 0
A19: 2.2.2. Сумма ежегодного списания затрат на общесистемное ПО, руб. | B19: РКПО 2 | C19: =D19+Q19*$Q$22+R19*$R$22+S19*$S$22+T19*$T$22 -> 0 | D19: =SUM(E19:P19)*$D$22 -> 0 | H19: ='Б1.1.1'!$B$39/'Б1.1.1'!$B$18 -> 0 | I19: ='Б1.1.1'!$B$39/'Б1.1.1'!$B$18 -> 0 | J19: ='Б1.1.1'!$B$39/'Б1.1.1'!$B$18 -> 0 | K19: ='Б1.1.1'!$B$39/'Б1.1.1'!$B$18 -> 0 | L19: ='Б1.1.1'!$B$39/'Б1.1.1'!$B$18 -> 0 | M19: ='Б1.1.1'!$B$39/'Б1.1.1'!$B$18 -> 0 | N19: ='Б1.1.1'!$B$39/'Б1.1.1'!$B$18 -> 0 | O19: ='Б1.1.1'!$B$39/'Б1.1.1'!$B$18 -> 0 | P19: ='Б1.1.1'!$B$39/'Б1.1.1'!$B$18 -> 0 | Q19: =$P$19*12 -> 0 | R19: =$P$19*12 -> 0 | S19: 0 | T19: 0 | U19: второй и последующие годы =месяц*12
A20: 2.2.3. Ежегодные затраты на аренду общесистемного ПО, руб. | B20: РКПО 3 | C20: =D20+Q20*$Q$22+R20*$R$22+S20*$S$22+T20*$T$22 -> 0 | D20: =SUM(E20:P20)*$D$22 -> 0 | H20: ='Б1.1.1'!$B$39/'Б1.1.1'!$B$18 -> 0 | I20: ='Б1.1.1'!$B$39/'Б1.1.1'!$B$18 -> 0 | J20: ='Б1.1.1'!$B$39/'Б1.1.1'!$B$18 -> 0 | K20: ='Б1.1.1'!$B$39/'Б1.1.1'!$B$18 -> 0 | L20: ='Б1.1.1'!$B$39/'Б1.1.1'!$B$18 -> 0 | M20: ='Б1.1.1'!$B$39/'Б1.1.1'!$B$18 -> 0 | N20: ='Б1.1.1'!$B$39/'Б1.1.1'!$B$18 -> 0 | O20: ='Б1.1.1'!$B$39/'Б1.1.1'!$B$18 -> 0 | P20: ='Б1.1.1'!$B$39/'Б1.1.1'!$B$18 -> 0 | Q20: =$P$19*12 -> 0 | R20: =$P$19*12 -> 0 | S20: 0 | T20: 0
A21: 2.2.4. Стоимость актуализации, поддержки и сопровождения общесистемного ПО за год, руб. | B21: РКПО 4 | C21: =D21+Q21*$Q$22+R21*$R$22+S21*$S$22+T21*$T$22 -> 0 | D21: =SUM(E21:P21)*$D$22 -> 0 | H21: ='Б1.1.1'!$B$39/'Б1.1.1'!$B$18 -> 0 | I21: ='Б1.1.1'!$B$39/'Б1.1.1'!$B$18 -> 0 | J21: ='Б1.1.1'!$B$39/'Б1.1.1'!$B$18 -> 0 | K21: ='Б1.1.1'!$B$39/'Б1.1.1'!$B$18 -> 0 | L21: ='Б1.1.1'!$B$39/'Б1.1.1'!$B$18 -> 0 | M21: ='Б1.1.1'!$B$39/'Б1.1.1'!$B$18 -> 0 | N21: ='Б1.1.1'!$B$39/'Б1.1.1'!$B$18 -> 0 | O21: ='Б1.1.1'!$B$39/'Б1.1.1'!$B$18 -> 0 | P21: ='Б1.1.1'!$B$39/'Б1.1.1'!$B$18 -> 0 | Q21: =$P$19*12 -> 0 | R21: =$P$19*12 -> 0 | S21: 0 | T21: 0
A22: 2.2.5. Коэффициент участия общесистемного ПО в подсистеме | B22: РУПО | C22: =(D22+Q22+R22+S22+T22)/5 -> 0.2 | D22: =SUM(E22:P22)/12 -> 0.2 | E22: 0.2 | F22: 0.2 | G22: 0.2 | H22: 0.2 | I22: 0.2 | J22: 0.2 | K22: 0.2 | L22: 0.2 | M22: 0.2 | N22: 0.2 | O22: 0.2 | P22: 0.2 | Q22: 0.2 | R22: 0.2 | S22: 0.2 | T22: 0.2
A23: 2.3. Косвенные административные расходы, руб. | B23: РКАдм | C23: =D23+Q23+R23+S23+T23 -> 515592 | D23: =SUM(D24:D27) -> 140616 | E23: =SUM(E24:E27)*E28 -> 0 | F23: =SUM(F24:F27)*F28 -> 0 | G23: =SUM(G24:G27)*G28 -> 0 | H23: =SUM(H24:H27)*H28 -> 15624 | I23: =SUM(I24:I27)*I28 -> 15624 | J23: =SUM(J24:J27)*J28 -> 15624 | K23: =SUM(K24:K27)*K28 -> 15624 | L23: =SUM(L24:L27)*L28 -> 15624 | ... T23: =SUM(T24:T27)*T28 -> 0
A24: 2.3.1. Расходы на оплату труда лиц, работающих со всей системой (общесистемный персонал), за год, руб. | B24: РКАдм 1 | C24: =D24+Q24*$Q$28+R24*$R$28+S24*$S$28+T24*$T$28 -> 515592 | D24: =SUM(E24:P24)*$D$28 -> 140616 | H24: ='Б1.1.1'!B34*'Б1.1.1'!$B$53*'Б1.1.1'!$B$41 -> 156240 | I24: ='Б1.1.1'!B34*'Б1.1.1'!$B$53*'Б1.1.1'!$B$41 -> 156240 | J24: ='Б1.1.1'!B34*'Б1.1.1'!$B$53*'Б1.1.1'!$B$41 -> 156240 | K24: ='Б1.1.1'!B34*'Б1.1.1'!$B$53*'Б1.1.1'!$B$41 -> 156240 | L24: ='Б1.1.1'!B34*'Б1.1.1'!$B$53*'Б1.1.1'!$B$41 -> 156240 | M24: ='Б1.1.1'!B34*'Б1.1.1'!$B$53*'Б1.1.1'!$B$41 -> 156240 | N24: ='Б1.1.1'!B34*'Б1.1.1'!$B$53*'Б1.1.1'!$B$41 -> 156240 | O24: ='Б1.1.1'!B34*'Б1.1.1'!$B$53*'Б1.1.1'!$B$41 -> 156240 | P24: ='Б1.1.1'!B34*'Б1.1.1'!$B$53*'Б1.1.1'!$B$41 -> 156240 | Q24: =O24*12 -> 1874880 | R24: =P24*12 -> 1874880 | W24: в год *12 мес
A25: 2.3.2. Расходы на консультационные услуги третьих фирм и аналогичные платежи за год, относящиеся ко всей системе организации, руб. | B25: РКАдм 2 | C25: =D25+Q25*$Q$28+R25*$R$28+S25*$S$28+T25*$T$28 -> 0 | D25: =SUM(E25:P25)*$D$28 -> 0
A26: 2.3.3. Ежегодные расходы на решение задач общесистемного характера, порученных другим организациям в порядке аутсорсинга, руб. | B26: РКАдм 3 | C26: =D26+Q26*$Q$28+R26*$R$28+S26*$S$28+T26*$T$28 -> 0 | D26: =SUM(E26:P26)*$D$28 -> 0
A27: 2.3.4. Ежегодные затраты на обучение персонала вопросам информационных технологий и систем информационного менеджмента в целом, руб. | B27: РКАдм 4 | C27: =D27+Q27*$Q$28+R27*$R$28+S27*$S$28+T27*$T$28 -> 0 | D27: =SUM(E27:P27)*$D$28 -> 0
A28: 2.3.5. Коэффициент участия общесистемного персонала в подсистеме | B28: РУАдм | C28: =(D28+Q28+R28+S28+T28)/5 -> 0.1 | D28: =SUM(E28:P28)/12 -> 0.1 | E28: 0.1 | F28: 0.1 | G28: 0.1 | H28: 0.1 | I28: 0.1 | J28: 0.1 | K28: 0.1 | L28: 0.1 | M28: 0.1 | N28: 0.1 | O28: 0.1 | P28: 0.1 | Q28: 0.1 | R28: 0.1 | S28: 0.1 | T28: 0.1
A29: 2.4. Косвенные расходы на оплату труда, связанные с сопровождением и развитием системы, руб. | B29: РКФОТ | C29: =C30+C33 -> 691687.5 | D29: =D30+D33 -> 27667.5 | E29: =E30*E36+E33*E36 -> 0 | F29: =F30*F36+F33*F36 -> 0 | G29: =G30*G36+G33*G36 -> 0 | H29: =H30*H36+H33*H36 -> 2766.75 | I29: =I30*I36+I33*I36 -> 2766.75 | J29: =J30*J36+J33*J36 -> 2766.75 | K29: =K30*K36+K33*K36 -> 2766.75 | L29: =L30*L36+L33*L36 -> 2766.75 | ... T29: =T30*T36+T33*T36 -> 0
A30: 2.4.1. Расходы на оплату труда сотрудников по сопровождению и развитию общесистемных ресурсов информационного менеджмента в течение года, руб., Всего в т.ч.: | B30: РКФОТ 1 | C30: =C31+C32 -> 691687.5 | D30: =SUM(D31:D32) -> 27667.5 | E30: =SUM(E31:E32) -> 0 | F30: =SUM(F31:F32) -> 0 | G30: =SUM(G31:G32) -> 0 | H30: =SUM(H31:H32) -> 27667.5 | I30: =SUM(I31:I32) -> 27667.5 | J30: =SUM(J31:J32) -> 27667.5 | K30: =SUM(K31:K32) -> 27667.5 | ... P30: =SUM(P31:P32) -> 55335 | Q30: =SUM(Q31+Q32) -> 332010 | R30: =SUM(R31+R32) -> 332010 | S30: =SUM(S31+S32) -> 0 | T30: =SUM(T31+T32) -> 0
A31: сопровождение | B31: РКФОТ 1_1 | C31: =D31+Q31+R31+S31+T31 -> 688920.75 | D31: =SUM(E31:P31)*$D$36 -> 24900.75 | H31: ='Б1.1.1'!$B$26*'Б1.1.1'!$B$27*'Б1.1.1'!$B$41 -> 27667.5 | I31: ='Б1.1.1'!$B$26*'Б1.1.1'!$B$27*'Б1.1.1'!$B$41 -> 27667.5 | J31: ='Б1.1.1'!$B$26*'Б1.1.1'!$B$27*'Б1.1.1'!$B$41 -> 27667.5 | K31: ='Б1.1.1'!$B$26*'Б1.1.1'!$B$27*'Б1.1.1'!$B$41 -> 27667.5 | L31: ='Б1.1.1'!$B$26*'Б1.1.1'!$B$27*'Б1.1.1'!$B$41 -> 27667.5 | M31: ='Б1.1.1'!$B$26*'Б1.1.1'!$B$27*'Б1.1.1'!$B$41 -> 27667.5 | N31: ='Б1.1.1'!$B$26*'Б1.1.1'!$B$27*'Б1.1.1'!$B$41 -> 27667.5 | O31: ='Б1.1.1'!$B$26*'Б1.1.1'!$B$27*'Б1.1.1'!$B$41 -> 27667.5 | P31: ='Б1.1.1'!$B$26*'Б1.1.1'!$B$27*'Б1.1.1'!$B$41 -> 27667.5 | Q31: =P31*12 -> 332010 | R31: =P31*12 -> 332010
A32: развитие | B32: РКФОТ 1_2 | C32: =D32+Q32+R32+S32+T32 -> 2766.75 | D32: =SUM(E32:P32)*$D$36 -> 2766.75 | P32: ='Б1.1.1'!$B$26*'Б1.1.1'!$B$27*'Б1.1.1'!$B$41 -> 27667.5
A33: 2.4.2. Расходы на оплату услуг сторонних консультантов и сервисных организаций в части развития и сопровождения общесистемных ресурсов информационного менеджмента в течение года, Всего в т.ч. | B33: РКФОТ 2 | C33: =C34+C35 -> 0 | D33: =SUM(D34:D35) -> 0 | E33: =SUM(E34:E35)*E$36 -> 0 | F33: =SUM(F34:F35)*F$36 -> 0 | G33: =SUM(G34:G35)*G$36 -> 0 | H33: =SUM(H34:H35)*H$36 -> 0 | I33: =SUM(I34:I35)*I$36 -> 0 | J33: =SUM(J34:J35)*J$36 -> 0 | K33: =SUM(K34:K35)*K$36 -> 0 | L33: =SUM(L34:L35)*L$36 -> 0 | ... P33: =SUM(P34:P35)*P$36 -> 0 | Q33: =SUM(Q34+Q35)*Q$36 -> 0 | R33: =SUM(R34+R35)*R$36 -> 0 | S33: =SUM(S34+S35)*S$36 -> 0 | T33: =SUM(T34+T35)*T$36 -> 0
A34: сопровождение | B34: РКФОТ 2_1 | C34: =D34+Q34*$Q$36+R34*$R$36+S34*$S$36+T34*$T$36 -> 0 | D34: =SUM(E34:P34)*$D$36 -> 0
A35: развитие | B35: РКФОТ 2_2 | C35: =D35+Q35*$Q$36+R35*$R$36+S35*$S$36+T35*$T$36 -> 0 | D35: =SUM(E35:P35)*$D$36 -> 0
A36: 2.4.5. Коэффициент участия общесистемных работ в разработке, развитии и сопровождении подсистемы | B36: КУФОТ | C36: =(D36+Q36+R36+S36+T36)/5 -> 0.1 | D36: =SUM(E36:P36)/12 -> 0.1 | E36: 0.1 | F36: 0.1 | G36: 0.1 | H36: 0.1 | I36: 0.1 | J36: 0.1 | K36: 0.1 | L36: 0.1 | M36: 0.1 | N36: 0.1 | O36: 0.1 | P36: 0.1 | Q36: 0.1 | R36: 0.1 | S36: 0.1 | T36: 0.1
A37: 2.5. Косвенные расходы на связь и коммуникации для рассматриваемой подсистемы (системы), руб. | B37: РККом | C37: =D37+Q37+R37+S37+T37 -> 0 | D37: =SUM(D38:D41) -> 0 | E37: =SUM(E38:E41)*E42 -> 0 | F37: =SUM(F38:F41)*F42 -> 0 | G37: =SUM(G38:G41)*G42 -> 0 | H37: =SUM(H38:H41)*H42 -> 0 | I37: =SUM(I38:I41)*I42 -> 0 | J37: =SUM(J38:J41)*J42 -> 0 | K37: =SUM(K38:K41)*K42 -> 0 | L37: =SUM(L38:L41)*L42 -> 0 | ... T37: =SUM(T38:T41)*T42 -> 0
A38: 2.5.1. Расходы на оплату труда персонала поддержки общей корпоративной сети, выделенных линий и каналов за год, руб. | B38: РККом 1 | C38: =D38+Q38*$Q$42+R38*$R$42+S38*$S$42+T38*$T$42 -> 0 | D38: =SUM(E38:P38)*$D$28 -> 0 | H38: ='Б1.1.1'!$B$32*'Б1.1.1'!$B$33*'Б1.1.1'!$B$41 -> 0 | I38: ='Б1.1.1'!$B$32*'Б1.1.1'!$B$33*'Б1.1.1'!$B$41 -> 0 | J38: ='Б1.1.1'!$B$32*'Б1.1.1'!$B$33*'Б1.1.1'!$B$41 -> 0 | K38: ='Б1.1.1'!$B$32*'Б1.1.1'!$B$33*'Б1.1.1'!$B$41 -> 0 | L38: ='Б1.1.1'!$B$32*'Б1.1.1'!$B$33*'Б1.1.1'!$B$41 -> 0 | M38: ='Б1.1.1'!$B$32*'Б1.1.1'!$B$33*'Б1.1.1'!$B$41 -> 0 | N38: ='Б1.1.1'!$B$32*'Б1.1.1'!$B$33*'Б1.1.1'!$B$41 -> 0 | O38: ='Б1.1.1'!$B$32*'Б1.1.1'!$B$33*'Б1.1.1'!$B$41 -> 0 | P38: ='Б1.1.1'!$B$32*'Б1.1.1'!$B$33*'Б1.1.1'!$B$41 -> 0 | Q38: =$P$38*12 -> 0 | R38: =$P$38*12 -> 0 | S38: 0 | T38: 0 | U38: в год *12 мес
A39: 2.5.2. Расходы на аренду выделенных общесистемных линий и каналов за год, руб. | B39: РККом 2 | C39: =D39+Q39*$Q$42+R39*$R$42+S39*$S$42+T39*$T$42 -> 0 | D39: =SUM(E39:P39)*$D$28 -> 0 | H39: 0 | I39: 0 | J39: 0 | K39: 0 | L39: 0 | M39: 0 | N39: 0 | O39: 0 | P39: 0 | Q39: 0 | R39: 0 | S39: 0 | T39: 0
A40: 2.5.3. Расходы на удаленный общесистемный доступ за год, руб. | B40: РККом 3 | C40: =D40+Q40*$Q$42+R40*$R$42+S40*$S$42+T40*$T$42 -> 0 | D40: =SUM(E40:P40)*$D$28 -> 0 | H40: 0 | I40: 0 | J40: 0 | K40: 0 | L40: 0 | M40: 0 | N40: 0 | O40: 0 | P40: 0 | Q40: 0 | R40: 0 | S40: 0 | T40: 0
A41: 2.5.4. Годовая стоимость поддержки и развития общесистемных корпоративных сетей передачи данных, руб. | B41: РККом 4 | C41: =D41+Q41*$Q$42+R41*$R$42+S41*$S$42+T41*$T$42 -> 0 | D41: =SUM(E41:P41)*$D$28 -> 0 | H41: 0 | I41: 0 | J41: 0 | K41: 0 | L41: 0 | M41: 0 | N41: 0 | O41: 0 | P41: 0 | Q41: 0 | R41: 0 | S41: 0 | T41: 0
A42: 2.5.5. Коэффициент участия общесистемных работ по коммуникациям в разработке, развитии и сопровождении подсистемы | B42: КУКом | C42: =(D42+Q42+R42+S42+T42)/5 -> 0.1 | D42: =SUM(E42:P42)/12 -> 0.1 | E42: 0.1 | F42: 0.1 | G42: 0.1 | H42: 0.1 | I42: 0.1 | J42: 0.1 | K42: 0.1 | L42: 0.1 | M42: 0.1 | N42: 0.1 | O42: 0.1 | P42: 0.1 | Q42: 0.1 | R42: 0.1 | S42: 0.1 | T42: 0.1

Sheet В1.2.3
T1: Таблица В 1.2.3
A3: Расчет расходов (непредвиденных), связанных с эксплуатацией ИТ-проекта
A5: Статья затрат | B5: Обозна- чение | C5: Всего | D5: в т.ч. по периодам эксплуатации системы
D6: 1 год, всего | E6: в т.ч. по периодам (месяцам) 1-го года жизни решения | Q6: 2 | R6: 3 | S6: 4 | T6: 5
E7: 1 месяц (разработка) | F7: 2 месяц (разработка) | G7: 3 месяц (разработка) | H7: 4 месяц | I7: 5 месяц | J7: 6 месяц | K7: 7 месяц | L7: 8 месяц | M7: 9 месяц | N7: 10 месяц | O7: 11 месяц | P7: 12 месяц
A8: 3. Непредвиденные расходы, руб. | B8: РНепр | C8: =C9+C12 -> 805.6125 | D8: =D9+D12 -> 219.7125 | E8: =E9+E12 -> 0 | F8: =F9+F12 -> 0 | G8: =G9+G12 -> 0 | H8: =H9+H12 -> 24.4125 | I8: =I9+I12 -> 24.4125 | J8: =J9+J12 -> 24.4125 | ... T8: =T9+T12 -> 0
A9: 3.1. Расходы на операции конечных пользователей | B9: РПольз | C9: =SUM(C10:C11) -> 0 | D9: =SUM(D10:D11) -> 0 | E9: =SUM(E10:E11) -> 0 | F9: =SUM(F10:F11) -> 0 | G9: =SUM(G10:G11) -> 0 | H9: =SUM(H10:H11) -> 0 | I9: =SUM(I10:I11) -> 0 | J9: =SUM(J10:J11) -> 0 | ... T9: =SUM(T10:T11) -> 0
A10: 3.1.1. Сумма оплаты труда, в соответствии с количеством часов, затраченных на самообучение сотрудников | B10: РПольз 1 | C10: =D10+Q10+R10+S10+T10 -> 0 | D10: =SUM(E10:P10) -> 0 | H10: ='Б1.1.1'!$B$45*'Б1.1.1'!$B$31*'Б1.1.1'!$B$41 -> 0 | I10: ='Б1.1.1'!$B$45*'Б1.1.1'!$B$31*'Б1.1.1'!$B$41 -> 0 | J10: ='Б1.1.1'!$B$45*'Б1.1.1'!$B$31*'Б1.1.1'!$B$41 -> 0 | K10: ='Б1.1.1'!$B$45*'Б1.1.1'!$B$31*'Б1.1.1'!$B$41 -> 0 | L10: ='Б1.1.1'!$B$45*'Б1.1.1'!$B$31*'Б1.1.1'!$B$41 -> 0 | M10: ='Б1.1.1'!$B$45*'Б1.1.1'!$B$31*'Б1.1.1'!$B$41 -> 0 | N10: ='Б1.1.1'!$B$45*'Б1.1.1'!$B$31*'Б1.1.1'!$B$41 -> 0 | O10: ='Б1.1.1'!$B$45*'Б1.1.1'!$B$31*'Б1.1.1'!$B$41 -> 0 | P10: ='Б1.1.1'!$B$45*'Б1.1.1'!$B$31*'Б1.1.1'!$B$41 -> 0 | Q10: =P10*12 -> 0 | R10: =Q10 -> 0 | U10: в год *12 мес
A11: 3.1.2. Сумма оплаты труда, соответствующая количеству часов на обслуживание файлов, компьютера и программ | B11: РПольз 2 | C11: =D11+Q11+R11+S11+T11 -> 0 | D11: =SUM(E11:P11) -> 0 | H11: ='Б1.1.1'!$B$46*'Б1.1.1'!$B$31*'Б1.1.1'!$B$41 -> 0 | I11: ='Б1.1.1'!$B$46*'Б1.1.1'!$B$31*'Б1.1.1'!$B$41 -> 0 | J11: ='Б1.1.1'!$B$46*'Б1.1.1'!$B$31*'Б1.1.1'!$B$41 -> 0 | K11: ='Б1.1.1'!$B$46*'Б1.1.1'!$B$31*'Б1.1.1'!$B$41 -> 0 | L11: ='Б1.1.1'!$B$46*'Б1.1.1'!$B$31*'Б1.1.1'!$B$41 -> 0 | M11: ='Б1.1.1'!$B$46*'Б1.1.1'!$B$31*'Б1.1.1'!$B$41 -> 0 | N11: ='Б1.1.1'!$B$46*'Б1.1.1'!$B$31*'Б1.1.1'!$B$41 -> 0 | O11: ='Б1.1.1'!$B$46*'Б1.1.1'!$B$31*'Б1.1.1'!$B$41 -> 0 | P11: ='Б1.1.1'!$B$46*'Б1.1.1'!$B$31*'Б1.1.1'!$B$41 -> 0 | Q11: =P11*12 -> 0 | R11: =Q11 -> 0 | U11: в год *12 мес
A12: 3.2. Расходы на простои | B12: РПрос | C12: =SUM(C13:C14) -> 805.6125 | D12: =SUM(D13:D14) -> 219.7125 | E12: =SUM(E13:E14) -> 0 | F12: =SUM(F13:F14) -> 0 | G12: =SUM(G13:G14) -> 0 | H12: =SUM(H13:H14) -> 24.4125 | I12: =SUM(I13:I14) -> 24.4125 | J12: =SUM(J13:J14) -> 24.4125 | ... T12: =SUM(T13:T14) -> 0
A13: 3.2.1. Затраты по количеству часов простоя в соответствии с плановыми или внеплановыми остановками в работе | B13: РПрос 1 | C13: =D13+Q13+R13+S13+T13 -> 805.6125 | D13: =SUM(E13:P13) -> 219.7125 | H13: ='Б1.1.1'!$B$33*'Б1.1.1'!$B$42*'Б1.1.1'!$B$30*'Б1.1.1'!$B$31*'Б1.1.1'!$B$41 -> 24.4125 | I13: ='Б1.1.1'!$B$33*'Б1.1.1'!$B$42*'Б1.1.1'!$B$30*'Б1.1.1'!$B$31*'Б1.1.1'!$B$41 -> 24.4125 | J13: ='Б1.1.1'!$B$33*'Б1.1.1'!$B$42*'Б1.1.1'!$B$30*'Б1.1.1'!$B$31*'Б1.1.1'!$B$41 -> 24.4125 | K13: ='Б1.1.1'!$B$33*'Б1.1.1'!$B$42*'Б1.1.1'!$B$30*'Б1.1.1'!$B$31*'Б1.1.1'!$B$41 -> 24.4125 | L13: ='Б1.1.1'!$B$33*'Б1.1.1'!$B$42*'Б1.1.1'!$B$30*'Б1.1.1'!$B$31*'Б1.1.1'!$B$41 -> 24.4125 | M13: ='Б1.1.1'!$B$33*'Б1.1.1'!$B$42*'Б1.1.1'!$B$30*'Б1.1.1'!$B$31*'Б1.1.1'!$B$41 -> 24.4125 | N13: ='Б1.1.1'!$B$33*'Б1.1.1'!$B$42*'Б1.1.1'!$B$30*'Б1.1.1'!$B$31*'Б1.1.1'!$B$41 -> 24.4125 | O13: ='Б1.1.1'!$B$33*'Б1.1.1'!$B$42*'Б1.1.1'!$B$30*'Б1.1.1'!$B$31*'Б1.1.1'!$B$41 -> 24.4125 | P13: ='Б1.1.1'!$B$33*'Б1.1.1'!$B$42*'Б1.1.1'!$B$30*'Б1.1.1'!$B$31*'Б1.1.1'!$B$41 -> 24.4125 | Q13: =P13*12 -> 292.95 | R13: =Q13 -> 292.95 | U13: в год *12 мес
A14: 3.2.2. Затраты, соответствующие количеству часов потерь в работе пользователя по вине работника или нехватке возможностей системы | B14: РПрос 2 | C14: =D14+Q14+R14+S14+T14 -> 0 | D14: =SUM(E14:P14) -> 0 | H14: ='Б1.1.1'!$B$43*'Б1.1.1'!$B$33*'Б1.1.1'!$B$31*'Б1.1.1'!$B$30*'Б1.1.1'!$B$41 -> 0 | I14: ='Б1.1.1'!$B$43*'Б1.1.1'!$B$33*'Б1.1.1'!$B$31*'Б1.1.1'!$B$30*'Б1.1.1'!$B$41 -> 0 | J14: ='Б1.1.1'!$B$43*'Б1.1.1'!$B$33*'Б1.1.1'!$B$31*'Б1.1.1'!$B$30*'Б1.1.1'!$B$41 -> 0 | K14: ='Б1.1.1'!$B$43*'Б1.1.1'!$B$33*'Б1.1.1'!$B$31*'Б1.1.1'!$B$30*'Б1.1.1'!$B$41 -> 0 | L14: ='Б1.1.1'!$B$43*'Б1.1.1'!$B$33*'Б1.1.1'!$B$31*'Б1.1.1'!$B$30*'Б1.1.1'!$B$41 -> 0 | M14: ='Б1.1.1'!$B$43*'Б1.1.1'!$B$33*'Б1.1.1'!$B$31*'Б1.1.1'!$B$30*'Б1.1.1'!$B$41 -> 0 | N14: ='Б1.1.1'!$B$43*'Б1.1.1'!$B$33*'Б1.1.1'!$B$31*'Б1.1.1'!$B$30*'Б1.1.1'!$B$41 -> 0 | O14: ='Б1.1.1'!$B$43*'Б1.1.1'!$B$33*'Б1.1.1'!$B$31*'Б1.1.1'!$B$30*'Б1.1.1'!$B$41 -> 0 | P14: ='Б1.1.1'!$B$43*'Б1.1.1'!$B$33*'Б1.1.1'!$B$31*'Б1.1.1'!$B$30*'Б1.1.1'!$B$41 -> 0 | Q14: =P14*12 -> 0 | R14: =Q14 -> 0 | U14: в год *12 мес

Sheet В1.3.1
T2: Таблица В1.3.1
A3: Расчет совокупной стоимости владения программного решения
A5: Наименование | B5: Обозна- чение | C5: Всего | D5: в т.ч. по периодам (годам) срока жизни решения
D6: 1 год всего | E6: в т.ч. по периодам (месяцам) 1-го года жизни решения | Q6: 2 | R6: 3 | S6: 4 | T6: 5
E7: 1 месяц | F7: 2 месяц | G7: 3 месяц | H7: 4 месяц | I7: 5 месяц | J7: 6 месяц | K7: 7 месяц | L7: 8 месяц | M7: 9 месяц | N7: 10 месяц | O7: 11 месяц | P7: 12 месяц
A8: Всего расходов, в т.ч. | B8: ССВ | C8: =D8+Q8+R8+S8+T8 -> 10260548 | D8: =SUM(D9:D12) -> 3838586.3 | E8: =SUM(E9:E12) -> 475111.3 | F8: =SUM(F9:F12) -> 364441.3 | G8: =SUM(G9:G12) -> 585781.3 | H8: =SUM(H9:H12) -> 265909.49 | I8: =SUM(I9:I12) -> 265909.49 | J8: =SUM(J9:J12) -> 268676.24 | K8: =SUM(K9:K12) -> 265909.49 | ... T8: =SUM(T9:T12) -> 0
A9: 1. Условно-прямые расходы (разработка), руб. | B9: РПр_Р | C9: =D9+Q9+R9+S9+T9 -> 1425333.9 | D9: =SUM(E9:P9) -> 1425333.9 | E9: ='В1.1.1'!D7 -> 475111.3 | F9: ='В1.1.1'!E7 -> 364441.3 | G9: ='В1.1.1'!F7 -> 585781.3 | H9: ='В1.1.1'!G7 -> 0 | I9: ='В1.1.1'!H7 -> 0 | J9: ='В1.1.1'!I7 -> 0 | K9: ='В1.1.1'!J7 -> 0 | L9: ='В1.1.1'!K7 -> 0 | ... P9: ='В1.1.1'!O7 -> 0
A10: 2. Условно-прямые расходы (эксплуатация), руб. | B10: РПр_Э | C10: =D10+Q10+R10+S10+T10 -> 1046570.9 | D10: =SUM(E10:P10) -> 285428.44 | E10: ='В1.2.1'!E8 -> 0 | F10: ='В1.2.1'!F8 -> 0 | G10: ='В1.2.1'!G8 -> 0 | H10: ='В1.2.1'!H8 -> 30792.021 | I10: ='В1.2.1'!I8 -> 30792.021 | J10: ='В1.2.1'!J8 -> 33558.771 | K10: ='В1.2.1'!K8 -> 30792.021 | L10: ='В1.2.1'!L8 -> 30792.021 | ... T10: ='В1.2.1'!T8 -> 0
A11: 3. Условно-косвенные расходы по системе, руб. | B11: РКос | C11: =D11+Q11+R11+S11+T11 -> 7787837.6 | D11: =SUM(E11:P11) -> 2127604.3 | E11: ='В1.2.2'!E8 -> 0 | F11: ='В1.2.2'!F8 -> 0 | G11: ='В1.2.2'!G8 -> 0 | H11: ='В1.2.2'!H8 -> 235093.06 | I11: ='В1.2.2'!I8 -> 235093.06 | J11: ='В1.2.2'!J8 -> 235093.06 | K11: ='В1.2.2'!K8 -> 235093.06 | L11: ='В1.2.2'!L8 -> 235093.06 | ... T11: ='В1.2.2'!T8 -> 0
A12: 4. Непредвиденные расходы, руб. | B12: РНепр | C12: =D12+Q12+R12+S12+T12 -> 805.6125 | D12: =SUM(E12:P12) -> 219.7125 | E12: ='В1.2.3'!E8 -> 0 | F12: ='В1.2.3'!F8 -> 0 | G12: ='В1.2.3'!G8 -> 0 | H12: ='В1.2.3'!H8 -> 24.4125 | I12: ='В1.2.3'!I8 -> 24.4125 | J12: ='В1.2.3'!J8 -> 24.4125 | K12: ='В1.2.3'!K8 -> 24.4125 | L12: ='В1.2.3'!L8 -> 24.4125 | ... T12: ='В1.2.3'!T8 -> 0
A13: ССВ на одно рабочее место | B13: ссв | C13: =C8/$Q$15 -> 256.5137 | D13: =D8/$Q$15 -> 95.964658 | Q13: =Q8/$Q$15 -> 80.274522 | R13: =R8/$Q$15 -> 80.274522 | S13: =S8/$Q$15 -> 0 | T13: =T8/$Q$15 -> 0
D15: m= | Q15: ='Б1.1.1'!B52 -> 40000 | R15: количество рабочих мест

Sheet Г1.1.1
D1: Таблица Г 1.1.1
A3: Расчет себестоимости бизнес-процесса по существующему варианту
A5: Наименование показателя | B5: Обозначение | C5: Всего в год | D5: в т.ч. в месяц
A7: 1. Себестоимость бизнес-процесса, руб. | B7: COFОт | C7: =SUM(C8:C12) -> 12749184 | D7: =SUM(D8:D12) -> 1062432
A8: 2.Расходные материалы | B8: COFОт_М | C8: ='Б1.1.1'!B13*12 -> 0 | D8: =C8/12 -> 0
A9: 3.Заработная плата персонала, участвующего в реализации бизнес-процесса | B9: COFОт_ФОТ | C9: =SUM('Б1.1.1'!B19:B22)*'Б1.1.1'!B23*12 -> 8160000 | D9: =C9/12 -> 680000
A10: 4.Начисления на заработную плату (страховые взносы) | B10: COFОт_СтрахВ | C10: =C9*0.302 -> 2464320 | D10: =C10/12 -> 205360
A11: 5.Содержание и эксплуатация информационных систем, используемых при реализации бизнес-процесса по старой схеме (без учета ФОТа персонала, указ. в п.3) | B11: COFОт_Экс_ИС | C11: 0 | D11: =C11/12 -> 0
A12: Накладные расходы, 20% от суммы п.2-п.5. | B12: COFОт_Накл | C12: =SUM(C8:C11)*0.2 -> 2124864 | D12: =$C$12/12 -> 177072

Sheet Д1.1.1
J1: Таблица Д 1.1.1
A3: Определение источников и сумм финансирования ИТ-проекта
A5: Наименование показателя | B5: Обозна- чение | C5: Алгоритм расчета | D5: Всего | E5: в т.ч. по периодам (месяцам) разработки системы
E6: 1 | F6: 2 | G6: 3 | H6: 4 | I6: 5 | J6: 6
A7: 1. Расходы, связанные с разработкой проекта, руб. | B7: РПр_Р | D7: ='В1.1.1'!C7 -> 1425333.9 | E7: ='В1.1.1'!D7 -> 475111.3 | F7: ='В1.1.1'!E7 -> 364441.3 | G7: ='В1.1.1'!F7 -> 585781.3 | H7: ='В1.1.1'!G7 -> 0 | I7: ='В1.1.1'!H7 -> 0 | J7: ='В1.1.1'!I7 -> 0
A8: 2. Источники финансирования расходов, руб. Всего в т.ч. | B8: S | D8: =SUM(D9:D10) -> 1425333.9 | E8: =SUM(E9:E10) -> 475111.3 | F8: =SUM(F9:F10) -> 364441.3 | G8: =SUM(G9:G10) -> 585781.3 | H8: =SUM(H9:H10) -> 0 | I8: =SUM(I9:I10) -> 0 | J8: =SUM(J9:J10) -> 0
A9: 2.1 Собственные средства, руб. | B9: SСоб | D9: =SUM(E9:J9) -> 88000 | E9: =E7-E10 -> 28000 | F9: =F7-F10 -> 25000 | G9: =G7-G10 -> 35000 | H9: 0 | I9: 0 | J9: 0
A10: 2.2 Заемные средства, руб. | B10: SПрив | D10: =SUM(E10:J10) -> 1337333.9 | E10: =E7-28000 -> 447111.3 | F10: =F7-25000 -> 339441.3 | G10: =G7-35000 -> 550781.3 | H10: 0 | I10: 0 | J10: 0
A11: 3.Доля собственных средств в структуре финансирования проекта,% | B11: dSCоб | D11: =D9/D8 -> 0.061739919 | E11: =E9/E8 -> 0.058933559 | F11: =F9/F8 -> 0.068598153 | G11: =G9/G8 -> 0.059749261 | H11: =H9/H8 -> #DIV/0! | I11: =I9/I8 -> #DIV/0! | J11: =J9/J8 -> #DIV/0!
A12: 4.Доля заемных средств в структуре финансирования проекта,% | B12: dSПрив | D12: =D10/D8 -> 0.93826008 | E12: =E10/E8 -> 0.94106644 | F12: =F10/F8 -> 0.93140185 | G12: =G10/G8 -> 0.94025074 | H12: =H10/H8 -> #DIV/0! | I12: =I10/I8 -> #DIV/0! | J12: =J10/J8 -> #DIV/0!

Sheet Е1.1.1 и 1.1.2
T1: Таблица Е 1.1.1
A3: Расчет чистого денежного потока для ИТ-проекта типа 1
A5: Наименование показателя | B5: Обозна- чение | C5: Всего | D5: в т.ч. по периодам (годам) жизненного цикла решения
D6: 1 год всего | E6: в т.ч. по периодам (месяцам) 1-го года жизни решения | Q6: 2 | R6: 3 | S6: 4 | T6: 5
E7: 1 месяц | F7: 2 месяц | G7: 3 месяц | H7: 4 месяц | I7: 5 месяц | J7: 6 месяц | K7: 7 месяц | L7: 8 месяц | M7: 9 месяц | N7: 10 месяц | O7: 11 месяц | P7: 12 месяц
A8: 1. Поступления (доходы), связанные с реализацией проекта, руб. | B8: CIFП | C8: =D8+Q8+R8+S8+T8 -> 0 | D8: =SUM(E8:P8) -> 0 | E8: 0 | F8: 0 | G8: 0 | H8: 0 | I8: 0 | J8: 0 | K8: 0 | L8: 0 | M8: 0 | N8: 0 | O8: 0 | P8: 0 | Q8: 0 | R8: 0 | S8: 0 | T8: 0
A9: 2.Амортизация оборудования и суммы ежегодного списания затрат на ПО | B9: COFАм | C9: =D9+Q9+R9+S9+T9 -> 7188660.2 | D9: =SUM(E9:P9) -> 1960543.7 | E9: ='В1.1.1'!D10+'В1.1.1'!D17 -> 0 | F9: ='В1.1.1'!E10+'В1.1.1'!E17 -> 0 | G9: ='В1.1.1'!F10+'В1.1.1'!F17 -> 0 | H9: ='В1.2.1'!H11+'В1.2.1'!H18+'В1.2.2'!H11*'В1.2.2'!H16+'В1.2.2'!H19*'В1.2.2'!H22 -> 217838.19 | I9: ='В1.2.1'!I11+'В1.2.1'!I18+'В1.2.2'!I11*'В1.2.2'!I16+'В1.2.2'!I19*'В1.2.2'!I22 -> 217838.19 | J9: ='В1.2.1'!J11+'В1.2.1'!J18+'В1.2.2'!J11*'В1.2.2'!J16+'В1.2.2'!J19*'В1.2.2'!J22 -> 217838.19 | K9: ='В1.2.1'!K11+'В1.2.1'!K18+'В1.2.2'!K11*'В1.2.2'!K16+'В1.2.2'!K19*'В1.2.2'!K22 -> 217838.19 | L9: ='В1.2.1'!L11+'В1.2.1'!L18+'В1.2.2'!L11*'В1.2.2'!L16+'В1.2.2'!L19*'В1.2.2'!L22 -> 217838.19 | M9: ='В1.2.1'!M11+'В1.2.1'!M18+'В1.2.2'!M11*'В1.2.2'!M16+'В1.2.2'!M19*'В1.2.2'!M22 -> 217838.19 | N9: ='В1.2.1'!N11+'В1.2.1'!N18+'В1.2.2'!N11*'В1.2.2'!N16+'В1.2.2'!N19*'В1.2.2'!N22 -> 217838.19 | O9: ='В1.2.1'!O11+'В1.2.1'!O18+'В1.2.2'!O11*'В1.2.2'!O16+'В1.2.2'!O19*'В1.2.2'!O22 -> 217838.19 | ... T9: ='В1.2.1'!T11+'В1.2.1'!T18+'В1.2.2'!T11*'В1.2.2'!T16+'В1.2.2'!T19*'В1.2.2'!T22 -> 0
A10: 3. Расходы, связанные с разработкой (внедрением) ИТ-проекта, руб (по данным табл. 1.1.1) | B10: COFП_Р | C10: =D10+Q10+R10+S10+T10 -> 1425333.9 | D10: =SUM(E10:P10) -> 1425333.9 | E10: ='В1.1.1'!D7-'В1.1.1'!D10-'В1.1.1'!D17 -> 475111.3 | F10: ='В1.1.1'!E7-'В1.1.1'!E10-'В1.1.1'!E17 -> 364441.3 | G10: ='В1.1.1'!F7-'В1.1.1'!F10-'В1.1.1'!F17 -> 585781.3 | H10: =H26 -> 0 | I10: =I26 -> 0 | J10: =J26 -> 0 | K10: =K26 -> 0 | L10: =L26 -> 0 | M10: =M26 -> 0 | N10: =N26 -> 0 | O10: =O26 -> 0 | P10: =P26 -> 0 | Q10: 0 | R10: 0 | S10: 0 | T10: 0
A11: 4. Расходы, связанные с сопровождением (эксплуатацией) ИТ-проекта, руб (по данным табл. 1.2.1+1.2.2.+.1.2.3) | B11: COFП_Э | C11: =D11+Q11+R11+S11+T11 -> 1646554 | D11: =SUM(E11:P11) -> 452708.72 | E11: =E27 -> 0 | F11: =F27 -> 0 | G11: =G27 -> 0 | H11: ='В1.3.1'!H8-'В1.2.1'!H11-'В1.2.1'!H18-'В1.2.2'!H11*'В1.2.2'!H16-'В1.2.2'!H19*'В1.2.2'!H22 -> 48071.303 | I11: ='В1.3.1'!I8-'В1.2.1'!I11-'В1.2.1'!I18-'В1.2.2'!I11*'В1.2.2'!I16-'В1.2.2'!I19*'В1.2.2'!I22 -> 48071.303 | J11: ='В1.3.1'!J8-'В1.2.1'!J11-'В1.2.1'!J18-'В1.2.2'!J11*'В1.2.2'!J16-'В1.2.2'!J19*'В1.2.2'!J22 -> 50838.053 | K11: ='В1.3.1'!K8-'В1.2.1'!K11-'В1.2.1'!K18-'В1.2.2'!K11*'В1.2.2'!K16-'В1.2.2'!K19*'В1.2.2'!K22 -> 48071.303 | L11: ='В1.3.1'!L8-'В1.2.1'!L11-'В1.2.1'!L18-'В1.2.2'!L11*'В1.2.2'!L16-'В1.2.2'!L19*'В1.2.2'!L22 -> 48071.303 | M11: ='В1.3.1'!M8-'В1.2.1'!M11-'В1.2.1'!M18-'В1.2.2'!M11*'В1.2.2'!M16-'В1.2.2'!M19*'В1.2.2'!M22 -> 50838.053 | N11: ='В1.3.1'!N8-'В1.2.1'!N11-'В1.2.1'!N18-'В1.2.2'!N11*'В1.2.2'!N16-'В1.2.2'!N19*'В1.2.2'!N22 -> 48071.303 | O11: ='В1.3.1'!O8-'В1.2.1'!O11-'В1.2.1'!O18-'В1.2.2'!O11*'В1.2.2'!O16-'В1.2.2'!O19*'В1.2.2'!O22 -> 48071.303 | ... T11: ='В1.3.1'!T8-'В1.2.1'!T11-'В1.2.1'!T18-'В1.2.2'!T11*'В1.2.2'!T16-'В1.2.2'!T19*'В1.2.2'!T22 -> 0
A12: 5.Чистый денежный поток, руб. | B12: СF | C12: =C8+C9-C10-C11 -> 4116772.3 | D12: =D8+D9-D10-D11 -> 82501.065 | E12: =E8+E9-E10-E11 -> -475111.3 | F12: =F8+F9-F10-F11 -> -364441.3 | G12: =G8+G9-G10-G11 -> -585781.3 | H12: =H8+H9-H10-H11 -> 169766.88 | I12: =I8+I9-I10-I11 -> 169766.88 | J12: =J8+J9-J10-J11 -> 167000.13 | ... T12: =T8+T9-T10-T11 -> 0
A13: 6.Чистый денежный поток нарастающим итогом, руб. | B13: СFC | D13: =D12 -> 82501.065 | E13: =E12 -> -475111.3 | F13: =E13+F12 -> -839552.6 | G13: =F13+G12 -> -1425333.9 | H13: =G13+H12 -> -1255567 | I13: =H13+I12 -> -1085800.1 | J13: =I13+J12 -> -918799.99 | K13: =J13+K12 -> -749033.11 | L13: =K13+L12 -> -579266.22 | M13: =L13+M12 -> -412266.09 | ... P13: =O13+P12 -> 82501.065 | Q13: =Q12+P13 -> 2099636.7 | R13: =R12+Q13 -> 4116772.3 | S13: =S12+R13 -> 4116772.3 | T13: =T12+S13 -> 4116772.3
B17: сверка | C17: =C9+C10+C11-C25-C26-C27 -> 0 | T17: Таблица Е 1.1.2
B18: сверка | C18: =C9-C25 -> 0
A19: Расчет чистого денежного потока для ИТ-проекта типа 2
A21: Наименование показателя | B21: Обозна- чение | C21: Всего | D21: в т.ч. по периодам (годам) жизненного цикла решения
D22: 1 год всего | E22: в т.ч. по периодам (месяцам) 1-го года жизни решения | Q22: 2 | R22: 3 | S22: 4 | T22: 5
E23: 1 месяц | F23: 2 месяц | G23: 3 месяц | H23: 4 месяц | I23: 5 месяц | J23: 6 месяц | K23: 7 месяц | L23: 8 месяц | M23: 9 месяц | N23: 10 месяц | O23: 11 месяц | P23: 12 месяц
A24: 1.Поступления (доходы) в случае реализации бизнес-процесса по схеме проекта, руб. | B24: CIFП | C24: =D24+Q24+R24+S24+T24 -> 0 | D24: =SUM(E24:P24) -> 0 | E24: 0 | F24: 0 | G24: 0 | H24: 0 | I24: 0 | J24: 0 | K24: 0 | L24: 0 | M24: 0 | N24: 0 | O24: 0 | P24: 0 | Q24: 0 | R24: 0 | S24: 0 | T24: 0
A25: 2.Амортизация оборудования и суммы ежегодного списания затрат на ПО | B25: COFАм | C25: =D25+Q25+R25+S25+T25 -> 7188660.2 | D25: =SUM(E25:P25) -> 1960543.7 | E25: ='В1.1.1'!D10+'В1.1.1'!D17 -> 0 | F25: ='В1.1.1'!E10+'В1.1.1'!E17 -> 0 | G25: ='В1.1.1'!F10+'В1.1.1'!F17 -> 0 | H25: ='В1.2.1'!H11+'В1.2.1'!H18+'В1.2.2'!H11*'В1.2.2'!H16+'В1.2.2'!H19*'В1.2.2'!H22 -> 217838.19 | I25: ='В1.2.1'!I11+'В1.2.1'!I18+'В1.2.2'!I11*'В1.2.2'!I16+'В1.2.2'!I19*'В1.2.2'!I22 -> 217838.19 | J25: ='В1.2.1'!J11+'В1.2.1'!J18+'В1.2.2'!J11*'В1.2.2'!J16+'В1.2.2'!J19*'В1.2.2'!J22 -> 217838.19 | K25: ='В1.2.1'!K11+'В1.2.1'!K18+'В1.2.2'!K11*'В1.2.2'!K16+'В1.2.2'!K19*'В1.2.2'!K22 -> 217838.19 | L25: ='В1.2.1'!L11+'В1.2.1'!L18+'В1.2.2'!L11*'В1.2.2'!L16+'В1.2.2'!L19*'В1.2.2'!L22 -> 217838.19 | M25: ='В1.2.1'!M11+'В1.2.1'!M18+'В1.2.2'!M11*'В1.2.2'!M16+'В1.2.2'!M19*'В1.2.2'!M22 -> 217838.19 | N25: ='В1.2.1'!N11+'В1.2.1'!N18+'В1.2.2'!N11*'В1.2.2'!N16+'В1.2.2'!N19*'В1.2.2'!N22 -> 217838.19 | O25: ='В1.2.1'!O11+'В1.2.1'!O18+'В1.2.2'!O11*'В1.2.2'!O16+'В1.2.2'!O19*'В1.2.2'!O22 -> 217838.19 | ... T25: ='В1.2.1'!T11+'В1.2.1'!T18+'В1.2.2'!T11*'В1.2.2'!T16+'В1.2.2'!T19*'В1.2.2'!T22 -> 0
A26: 3.Расходы, связанные с реализацией бизнес-процесса по схеме проекта (разработка), руб (по данным табл. 1.1.1) | B26: COFП_Р | C26: =D26+Q26+R26+S26+T26 -> 1425333.9 | D26: =SUM(E26:P26) -> 1425333.9 | E26: =E10 -> 475111.3 | F26: =F10 -> 364441.3 | G26: =G10 -> 585781.3 | H26: ='В1.1.1'!G7 -> 0 | I26: ='В1.1.1'!H7 -> 0 | J26: ='В1.1.1'!I7 -> 0 | K26: ='В1.1.1'!J7 -> 0 | L26: ='В1.1.1'!K7 -> 0 | M26: ='В1.1.1'!L7 -> 0 | N26: ='В1.1.1'!M7 -> 0 | O26: ='В1.1.1'!N7 -> 0 | P26: ='В1.1.1'!O7 -> 0 | Q26: 0 | R26: 0 | S26: 0 | T26: 0
A27: 4.Расходы, в случае реализации бизнес-процесса по схеме проекта (эксплуатация), руб (по данным табл. 1.2.1+1.2.2.+.1.2.3) | B27: COFП_Э | C27: =D27+Q27+R27+S27+T27 -> 1646554 | D27: =SUM(E27:P27) -> 452708.72 | E27: ='В1.2.1'!E8+'В1.2.2'!E8+'В1.2.3'!E8 -> 0 | F27: ='В1.2.1'!F8+'В1.2.2'!F8+'В1.2.3'!F8 -> 0 | G27: ='В1.2.1'!G8+'В1.2.2'!G8+'В1.2.3'!G8 -> 0 | H27: =H11 -> 48071.303 | I27: =I11 -> 48071.303 | J27: =J11 -> 50838.053 | K27: =K11 -> 48071.303 | L27: =L11 -> 48071.303 | M27: =M11 -> 50838.053 | N27: =N11 -> 48071.303 | O27: =O11 -> 48071.303 | ... T27: =T11 -> 0
A28: 5.Денежный поток в случае реализации бизнес-процесса по схеме проекта | B28: СFП | C28: =C24+C25-C26-C27 -> 4116772.3 | D28: =SUM(E28:P28) -> 82501.065 | E28: =E24+E25-E26-E27 -> -475111.3 | F28: =F24+F25-F26-F27 -> -364441.3 | G28: =G24+G25-G26-G27 -> -585781.3 | H28: =H24+H25-H26-H27 -> 169766.88 | I28: =I24+I25-I26-I27 -> 169766.88 | J28: =J24+J25-J26-J27 -> 167000.13 | K28: =K24+K25-K26-K27 -> 169766.88 | L28: =L24+L25-L26-L27 -> 169766.88 | ... T28: =T24+T25-T26-T27 -> 0
A29: 6.Поступления (доходы) в случае реализации бизнес-процесса по старой схеме, руб. | B29: CIFОт | C29: =SUM(D29:T29) -> 0 | D29: =SUM(E29:P29) -> 0 | E29: 0 | F29: 0 | G29: 0 | H29: 0 | I29: 0 | J29: 0 | K29: 0 | L29: 0 | M29: 0 | N29: 0 | O29: 0 | P29: 0 | Q29: 0 | R29: 0 | S29: 0 | T29: 0
A30: 7. Расходы, в случае реализации проекта по старой схеме, руб (по данным табл. Г 1.1.1 ) | B30: COFОт | C30: =D30+Q30+R30+S30+T30 -> 35060256 | D30: =SUM(E30:P30) -> 9561888 | E30: 0 | F30: 0 | G30: 0 | H30: ='Г1.1.1'!$D$7 -> 1062432 | I30: ='Г1.1.1'!$D$7 -> 1062432 | J30: ='Г1.1.1'!$D$7 -> 1062432 | K30: ='Г1.1.1'!$D$7 -> 1062432 | L30: ='Г1.1.1'!$D$7 -> 1062432 | M30: ='Г1.1.1'!$D$7 -> 1062432 | N30: ='Г1.1.1'!$D$7 -> 1062432 | O30: ='Г1.1.1'!$D$7 -> 1062432 | P30: ='Г1.1.1'!$D$7 -> 1062432 | Q30: ='Г1.1.1'!$C$7 -> 12749184 | R30: ='Г1.1.1'!$C$7 -> 12749184
A31: 8.Денежный поток в случае реализации бизнес-процесса по старой схеме | B31: СFОт | C31: =D31+Q31+R31+S31+T31 -> -35060256 | D31: =SUM(E31:P31) -> -9561888 | E31: =E29-E30 -> 0 | F31: =F29-F30 -> 0 | G31: =G29-G30 -> 0 | H31: =H29-H30 -> -1062432 | I31: =I29-I30 -> -1062432 | J31: =J29-J30 -> -1062432 | K31: =K29-K30 -> -1062432 | L31: =L29-L30 -> -1062432 | ... T31: =T29-T30 -> 0
A32: 9.Чистый денежный поток, руб. | B32: СF | C32: =D32+Q32+R32+S32+T32 -> 39177028 | D32: =SUM(E32:P32) -> 9644389.1 | E32: =E28-E31 -> -475111.3 | F32: =F28-F31 -> -364441.3 | G32: =G28-G31 -> -585781.3 | H32: =H28-H31 -> 1232198.9 | I32: =I28-I31 -> 1232198.9 | J32: =J28-J31 -> 1229432.1 | K32: =K28-K31 -> 1232198.9 | L32: =L28-L31 -> 1232198.9 | ... T32: =T28-T31 -> 0
A33: 10.Чистый денежный поток нарастающим итогом, руб. | B33: СFC | D33: =D32 -> 9644389.1 | E33: =E32 -> -475111.3 | F33: =E33+F32 -> -839552.6 | G33: =F33+G32 -> -1425333.9 | H33: =G33+H32 -> -193135.01 | I33: =H33+I32 -> 1039063.9 | J33: =I33+J32 -> 2268496 | K33: =J33+K32 -> 3500694.9 | L33: =K33+L32 -> 4732893.8 | M33: =L33+M32 -> 5962325.9 | ... R33: =Q33+R32 -> 39177028

Sheet Е1.2.1 - 1.2.3
C1: Таблица Е 1.2.1
A2: Расчет ставки дисконтирования
A4: Наименование показателя | B4: Обозна- чение | C4: Всего
A6: 1. Ставка дисконтирования, рассчитанная методом WACC | B6: r | C6: =C8*C10*(1-B12)+C7*C9 -> 0.11125912
A7: 3.Доля собственных средств в структуре финансирования,% | B7: wск | C7: ='Д1.1.1'!D11 -> 0.061739919
A8: 4.Доля заемных средств в структуре финансирования,% | B8: wзк | C8: ='Д1.1.1'!D12 -> 0.93826008
A9: 5.Стоимость, собственного капитала,% | B9: kck | C9: 0.1
A10: 6.Стоимость заемного капитала,% | B10: kзк | C10: 0.14
A12: ставка налога на прибыль при ОСНО t= | B12: 0.2
A14: величина инфляции h = | B14: ='Б1.1.1'!B44 -> 0.055 | G14: Таблица Е 1.2.2
A15: Расчет коэффициента дисконтирования по периодам срока жизни решения
A17: Наименование показателя | B17: Обозна- чение | C17: в т.ч. по периодам (годам) срока жизни решения
C18: 1 | D18: 2 | E18: 3 | F18: 4 | G18: 5
A19: 1.Ставка дисконтирования, рассчитанная методом WACC | B19: r | C19: =C6 -> 0.11125912 | D19: =C19 -> 0.11125912 | E19: =D19 -> 0.11125912 | F19: =E19 -> 0.11125912 | G19: =F19 -> 0.11125912
A20: 2. Коэффициент дисконтирования, посчитанный по ставке r | B20: kD | C20: 1 | D20: =1/(1+D19)^C18 -> 0.89988013 | E20: =1/(1+E19)^D18 -> 0.80978424 | F20: =1/(1+F19)^E18 -> 0.72870875 | G20: =1/(1+G19)^F18 -> 0.65575052
A21: 3.Ставка дисконтирования, скорректированная на инфляцию | B21: rкорр | C21: =C19+$B$14+C19*$B$14 -> 0.17237837 | D21: =C21 -> 0.17237837 | E21: =D21 -> 0.17237837 | F21: =E21 -> 0.17237837 | G21: =F21 -> 0.17237837
A22: 4. Коэффициент дисконтирования, посчитанный по ставке r корр | B22: kDкорр | C22: 1 | D22: =1/(1+D21)^C18 -> 0.85296695 | E22: =1/(1+E21)^D18 -> 0.72755261 | F22: =1/(1+F21)^E18 -> 0.62057833 | G22: =1/(1+G21)^F18 -> 0.5293328
N24: Таблица Е 1.2.3
A25: Расчет коэффициента дисконтирования (помесячно) для 1-го года жизни решения
A27: Наименование показателя | B27: Обозна- чение | C27: в т.ч. по периодам (месяцам) 1-го года жизни решения
C28: 1 | D28: 2 | E28: 3 | F28: 4 | G28: 5 | H28: 6 | I28: 7 | J28: 8 | K28: 9 | L28: 10 | M28: 11 | N28: 12
A29: 1.Ставка дисконтирования (месячная), рассчитанная методом WACC | B29: rмес | C29: =C19^1/12 -> 0.0092715934 | D29: =C29 -> 0.0092715934 | E29: =D29 -> 0.0092715934 | F29: =E29 -> 0.0092715934 | G29: =F29 -> 0.0092715934 | H29: =G29 -> 0.0092715934 | I29: =H29 -> 0.0092715934 | J29: =I29 -> 0.0092715934 | K29: =J29 -> 0.0092715934 | ... N29: =M29 -> 0.0092715934
A30: 2. Коэффициент дисконтирования, посчитанный по ставке r мес | B30: kDмес | C30: 1 | D30: =1/(1+D29)^C28 -> 0.99081358 | E30: =1/(1+E29)^D28 -> 0.98171155 | F30: =1/(1+F29)^E28 -> 0.97269313 | G30: =1/(1+G29)^F28 -> 0.96375757 | H30: =1/(1+H29)^G28 -> 0.95490408 | I30: =1/(1+I29)^H28 -> 0.94613193 | J30: =1/(1+J29)^I28 -> 0.93744037 | K30: =1/(1+K29)^J28 -> 0.92882864 | ... N30: =1/(1+N29)^M28 -> 0.90346525
A31: 3.Ставка дисконтирования (месячная), скорректированная на инфляцию | B31: rкорр_мес | C31: =C21^1/12 -> 0.014364864 | D31: =C31 -> 0.014364864 | E31: =D31 -> 0.014364864 | F31: =E31 -> 0.014364864 | G31: =F31 -> 0.014364864 | H31: =G31 -> 0.014364864 | I31: =H31 -> 0.014364864 | J31: =I31 -> 0.014364864 | K31: =J31 -> 0.014364864 | ... N31: =M31 -> 0.014364864
A32: 4. Коэффициент дисконтирования, посчитанный по ставке rкорр | B32: kDкорр_мес | C32: 1 | D32: =1/(1+D31)^C28 -> 0.98583856 | E32: =1/(1+E31)^D28 -> 0.97187767 | F32: =1/(1+F31)^E28 -> 0.95811449 | G32: =1/(1+G31)^F28 -> 0.94454621 | H32: =1/(1+H31)^G28 -> 0.93117008 | I32: =1/(1+I31)^H28 -> 0.91798337 | J32: =1/(1+J31)^I28 -> 0.90498341 | K32: =1/(1+K31)^J28 -> 0.89216754 | ... N32: =1/(1+N31)^M28 -> 0.85479865

Sheet Е1.3.1 - Е1.3.4
H1: Таблица Е 1.3.1
A3: Расчет дисконтированных и наращенных значений чистого денежного потока для ИТ-проекта типа 1
A5: Наименование показателя | B5: Обозна- чение | C5: Всего | D5: в т.ч. по периодам (годам) жизненного цикла решения
D6: 1 | E6: 2 | F6: 3 | G6: 4 | H6: 5
A7: 1.Чистый денежный поток, руб. | B7: СF | C7: ='Е1.1.1 и 1.1.2'!C12 -> 4116772.3 | D7: ='Е1.1.1 и 1.1.2'!D12 -> 82501.065 | E7: ='Е1.1.1 и 1.1.2'!Q12 -> 2017135.6 | F7: ='Е1.1.1 и 1.1.2'!R12 -> 2017135.6 | G7: ='Е1.1.1 и 1.1.2'!S12 -> 0 | H7: ='Е1.1.1 и 1.1.2'!T12 -> 0
A8: 2.Чистый денежный поток нарастающим итогом, руб. | B8: CFC | D8: =D7 -> 82501.065 | E8: =E7+D8 -> 2099636.7 | F8: =F7+E8 -> 4116772.3 | G8: =G7+F8 -> 4116772.3 | H8: =H7+G8 -> 4116772.3
A9: 3. Коэффициент дисконтирования, посчитанный по ставке r | B9: kD | D9: ='Е1.2.1 - 1.2.3'!C20 -> 1 | E9: ='Е1.2.1 - 1.2.3'!D20 -> 0.89988013 | F9: ='Е1.2.1 - 1.2.3'!E20 -> 0.80978424 | G9: ='Е1.2.1 - 1.2.3'!F20 -> 0.72870875 | H9: ='Е1.2.1 - 1.2.3'!G20 -> 0.65575052
A10: 4.Чистый дисконтированный денежный поток, руб. | B10: CFD | C10: =SUM(D10:H10) -> 3531126 | D10: =D9*D7 -> 82501.065 | E10: =E9*E7 -> 1815180.3 | F10: =F9*F7 -> 1633444.6 | G10: =G9*G7 -> 0 | H10: =H9*H7 -> 0
A11: 5.Чистый дисконтированный денежный поток нарастающим итогом, руб. | B11: CFD_C | D11: =D10 -> 82501.065 | E11: =D11+E10 -> 1897681.3 | F11: =E11+F10 -> 3531126 | G11: =F11+G10 -> 3531126 | H11: =G11+H10 -> 3531126
A12: 6. Дисконтируемые поступления (доходы), связанные с реализацией проекта, руб. | B12: CIFD | C12: =SUM(D12:H12) -> 6429705.9 | D12: =('Е1.1.1 и 1.1.2'!D8+'Е1.1.1 и 1.1.2'!D9)*D9 -> 1960543.7 | E12: =('Е1.1.1 и 1.1.2'!Q8+'Е1.1.1 и 1.1.2'!Q9)*E9 -> 2352339.1 | F12: =('Е1.1.1 и 1.1.2'!R8+'Е1.1.1 и 1.1.2'!R9)*F9 -> 2116823.2 | G12: =('Е1.1.1 и 1.1.2'!S8+'Е1.1.1 и 1.1.2'!S9)*G9 -> 0 | H12: =('Е1.1.1 и 1.1.2'!T8+'Е1.1.1 и 1.1.2'!T9)*H9 -> 0
A13: 7. Дисконтируемые эксплуатационные расходы проекта, руб | B13: COFэD | C13: =SUM(D13:H13) -> 1473246.1 | D13: =D9*('Е1.1.1 и 1.1.2'!D11) -> 452708.72 | E13: =E9*('Е1.1.1 и 1.1.2'!Q11) -> 537158.81 | F13: =F9*('Е1.1.1 и 1.1.2'!R11) -> 483378.54 | G13: =G9*('Е1.1.1 и 1.1.2'!S11) -> 0 | H13: =H9*('Е1.1.1 и 1.1.2'!T11) -> 0
A14: 8. Дисконтируемые инвестиционные расходы проекта, руб | B14: COFиD | C14: =SUM(D14:H14) -> 1425333.9 | D14: =D9*'Е1.1.1 и 1.1.2'!D10 -> 1425333.9 | E14: =E9*'Е1.1.1 и 1.1.2'!Q10 -> 0 | F14: =F9*'Е1.1.1 и 1.1.2'!R10 -> 0 | G14: =G9*'Е1.1.1 и 1.1.2'!S10 -> 0 | H14: =H9*'Е1.1.1 и 1.1.2'!T10 -> 0
A15: 9. Коэффициент наращения, посчитанный по ставке r | B15: kА | D15: =(1+'Е1.2.1 - 1.2.3'!$C$6)^($H$6-D6) -> 1.5249702 | E15: =(1+'Е1.2.1 - 1.2.3'!$C$6)^($H$6-E6) -> 1.3722904 | F15: =(1+'Е1.2.1 - 1.2.3'!$C$6)^($H$6-F6) -> 1.2348968 | G15: =(1+'Е1.2.1 - 1.2.3'!$C$6)^($H$6-G6) -> 1.1112591 | H15: =(1+'Е1.2.1 - 1.2.3'!$C$6)^($H$6-H6) -> 1
A16: 10.Чистый денежный поток, приведенный к моменту окончания проекта, руб. | B16: CFА | C16: =SUM(D16:H16) -> 5384861.8 | D16: =D15*D7 -> 125811.66 | E16: =E15*E7 -> 2768095.8 | F16: =F15*F7 -> 2490954.4 | G16: =G15*G7 -> 0 | H16: =H15*H7 -> 0
A17: 11.Чистый денежный поток нарастающим итогом, приведенный к моменту окончания проекта, руб. | B17: CFА_C | D17: =D16 -> 125811.66 | E17: =D17+E16 -> 2893907.5 | F17: =E17+F16 -> 5384861.8 | G17: =F17+G16 -> 5384861.8 | H17: =G17+H16 -> 5384861.8
H19: Таблица Е 1.3.2
A21: Расчет дисконтированных и наращенных значений чистого денежного потока для ИТ-проекта 2-го типа
A23: Наименование показателя | B23: Обозна- чение | C23: Всего | D23: в т.ч. по периодам (годам) жизненного цикла решения
D24: 1 | E24: 2 | F24: 3 | G24: 4 | H24: 5
A25: 1.Чистый денежный поток, руб. | B25: СF | C25: =SUM(D25:H25) -> 8804836.5 | D25: ='Е1.1.1 и 1.1.2'!D32 -> 9644389.1 | E25: ='Е1.1.1 и 1.1.2'!E32 -> -475111.3 | F25: ='Е1.1.1 и 1.1.2'!F32 -> -364441.3 | G25: ='Е1.1.1 и 1.1.2'!S32 -> 0 | H25: ='Е1.1.1 и 1.1.2'!T32 -> 0
A26: 2.Чистый денежный поток нарастающим итогом, руб. | B26: CFC | D26: ='Е1.1.1 и 1.1.2'!D33 -> 9644389.1 | E26: ='Е1.1.1 и 1.1.2'!Q33 -> 24410709 | F26: ='Е1.1.1 и 1.1.2'!R33 -> 39177028 | G26: ='Е1.1.1 и 1.1.2'!S33 -> 0 | H26: ='Е1.1.1 и 1.1.2'!T33 -> 0
A27: 3. Коэффициент дисконтирования, посчитанный по ставке r | B27: kD | D27: ='Е1.2.1 - 1.2.3'!C20 -> 1 | E27: ='Е1.2.1 - 1.2.3'!D20 -> 0.89988013 | F27: ='Е1.2.1 - 1.2.3'!E20 -> 0.80978424 | G27: ='Е1.2.1 - 1.2.3'!F20 -> 0.72870875 | H27: ='Е1.2.1 - 1.2.3'!G20 -> 0.65575052
A28: 4.Чистый дисконтированный денежный поток, руб. | B28: CFD | C28: =SUM(D28:H28) -> 8921727 | D28: =D27*D25 -> 9644389.1 | E28: =E27*E25 -> -427543.22 | F28: =F27*F25 -> -295118.82 | G28: =G27*G25 -> 0 | H28: =H27*H25 -> 0
A29: 5.Чистый дисконтировнный денежный поток нарастающим итогом, руб. | B29: CFD_C | D29: =D28 -> 9644389.1 | E29: =D29+E28 -> 9216845.8 | F29: =E29+F28 -> 8921727 | G29: =F29+G28 -> 8921727 | H29: =G29+H28 -> 8921727
A30: 6. Коэффициент наращения, посчитанный по ставке r | B30: kА | D30: =(1+'Е1.2.1 - 1.2.3'!$C$6)^($H$6-D24) -> 1.5249702 | E30: =(1+'Е1.2.1 - 1.2.3'!$C$6)^($H$6-E24) -> 1.3722904 | F30: =(1+'Е1.2.1 - 1.2.3'!$C$6)^($H$6-F24) -> 1.2348968 | G30: =(1+'Е1.2.1 - 1.2.3'!$C$6)^($H$6-G24) -> 1.1112591 | H30: =(1+'Е1.2.1 - 1.2.3'!$C$6)^($H$6-H24) -> 1
A31: 7.Чистый денежный поток, приведенный к моменту окончания проекта, руб. | B31: CFА | C31: =SUM(D31:H31) -> 13605368 | D31: =D30*D25 -> 14707406 | E31: =E30*E25 -> -651990.66 | F31: =F30*F25 -> -450047.41 | G31: =G30*G25 -> 0 | H31: =H30*H25 -> 0
A32: 8.Чистый денежный поток нарастающим итогом, приведенный к моменту окончания проекта, руб. | B32: CFА_C | D32: =D31 -> 14707406 | E32: =D32+E31 -> 14055415 | F32: =E32+F31 -> 13605368 | G32: =F32+G31 -> 13605368 | H32: =G32+H31 -> 13605368
O34: Таблица Е 1.3.3
A36: Расчет дисконтированных значений чистого денежного потока для ИТ-проекта 1-го типа по месяцам 1-го года жизни решения
A38: Наименование показателя | B38: Обозна- чение | C38: Всего за 1 год | D38: в т.ч. по периодам (месяцам) 1-го года жизни решения | P38: 2-го года жизни решения | AB38: 3-го года жизни решения | AN38: 4-го года жизни решения | AZ38: 5-го года жизни решения
D39: 1 месяц | E39: 2 месяц | F39: 3 месяц | G39: 4 месяц | H39: 5 месяц | I39: 6 месяц | J39: 7 месяц | K39: 8 месяц | L39: 9 месяц | M39: 10 месяц | N39: 11 месяц | O39: 12 месяц | P39: 1 | Q39: 2 | R39: 3 | S39: 4 | T39: 5 | U39: 6 | V39: 7 | W39: 8 | X39: 9 | Y39: 10 | Z39: 11 | AA39: 12 | AB39: 1 | AC39: 2 | AD39: 3 | AE39: 4 | AF39: 5 | AG39: 6 | AH39: 7 | AI39: 8 | AJ39: 9 | AK39: 10 | AL39: 11 | AM39: 12 | AN39: 1 | AO39: 2 | AP39: 3 | AQ39: 4 | AR39: 5 | AS39: 6 | AT39: 7 | AU39: 8 | AV39: 9 | AW39: 10 | AX39: 11 | AY39: 12 | AZ39: 1 | BA39: 2 | BB39: 3 | BC39: 4 | BD39: 5 | BE39: 6 | BF39: 7 | BG39: 8 | BH39: 9 | BI39: 10 | BJ39: 11 | BK39: 12
A40: 1.Чистый денежный поток, руб. | B40: СF | C40: =SUM(D40:O40) -> 82501.065 | D40: ='Е1.1.1 и 1.1.2'!E12 -> -475111.3 | E40: ='Е1.1.1 и 1.1.2'!F12 -> -364441.3 | F40: ='Е1.1.1 и 1.1.2'!G12 -> -585781.3 | G40: ='Е1.1.1 и 1.1.2'!H12 -> 169766.88 | H40: ='Е1.1.1 и 1.1.2'!I12 -> 169766.88 | I40: ='Е1.1.1 и 1.1.2'!J12 -> 167000.13 | J40: ='Е1.1.1 и 1.1.2'!K12 -> 169766.88 | K40: ='Е1.1.1 и 1.1.2'!L12 -> 169766.88 | ... O40: ='Е1.1.1 и 1.1.2'!P12 -> 155233.38 | P40: =$E$7/12 -> 168094.64 | Q40: =$E$7/12 -> 168094.64 | R40: =$E$7/12 -> 168094.64 | S40: =$E$7/12 -> 168094.64 | T40: =$E$7/12 -> 168094.64 | U40: =$E$7/12 -> 168094.64 | V40: =$E$7/12 -> 168094.64 | W40: =$E$7/12 -> 168094.64 | ... AA40: =$E$7/12 -> 168094.64 | AB40: =$F$7/12 -> 168094.64 | AC40: =$F$7/12 -> 168094.64 | AD40: =$F$7/12 -> 168094.64 | AE40: =$F$7/12 -> 168094.64 | AF40: =$F$7/12 -> 168094.64 | AG40: =$F$7/12 -> 168094.64 | AH40: =$F$7/12 -> 168094.64 | AI40: =$F$7/12 -> 168094.64 | ... AM40: =$F$7/12 -> 168094.64 | AN40: =$G$7/12 -> 0 | AO40: =$G$7/12 -> 0 | AP40: =$G$7/12 -> 0 | AQ40: =$G$7/12 -> 0 | AR40: =$G$7/12 -> 0 | AS40: =$G$7/12 -> 0 | AT40: =$G$7/12 -> 0 | AU40: =$G$7/12 -> 0 | ... AY40: =$G$7/12 -> 0 | AZ40: =$H$7/12 -> 0 | BA40: =$H$7/12 -> 0 | BB40: =$H$7/12 -> 0 | BC40: =$H$7/12 -> 0 | BD40: =$H$7/12 -> 0 | BE40: =$H$7/12 -> 0 | BF40: =$H$7/12 -> 0 | BG40: =$H$7/12 -> 0 | ... BK40: =$H$7/12 -> 0
A41: 2.Чистый денежный поток нарастающим итогом, руб. | B41: CFC | D41: =D40 -> -475111.3 | E41: =E40+D41 -> -839552.6 | F41: =F40+E41 -> -1425333.9 | G41: =G40+F41 -> -1255567 | H41: =H40+G41 -> -1085800.1 | I41: =I40+H41 -> -918799.99 | J41: =J40+I41 -> -749033.11 | K41: =K40+J41 -> -579266.22 | L41: =L40+K41 -> -412266.09 | ... O41: =O40+N41 -> 82501.065
A42: 3. Коэффициент дисконтирования, посчитанный по ставке r мес | B42: kD мес | D42: ='Е1.2.1 - 1.2.3'!C30 -> 1 | E42: ='Е1.2.1 - 1.2.3'!D30 -> 0.99081358 | F42: ='Е1.2.1 - 1.2.3'!E30 -> 0.98171155 | G42: ='Е1.2.1 - 1.2.3'!F30 -> 0.97269313 | H42: ='Е1.2.1 - 1.2.3'!G30 -> 0.96375757 | I42: ='Е1.2.1 - 1.2.3'!H30 -> 0.95490408 | J42: ='Е1.2.1 - 1.2.3'!I30 -> 0.94613193 | K42: ='Е1.2.1 - 1.2.3'!J30 -> 0.93744037 | ... O42: ='Е1.2.1 - 1.2.3'!N30 -> 0.90346525
A43: 4.Чистый дисконтированный денежный поток, руб. | B43: CFD | C43: =SUM(D43:O43) -> 3108.3712 | D43: =D42*D40 -> -475111.3 | E43: =E42*E40 -> -361093.39 | F43: =F42*F40 -> -575068.27 | G43: =G42*G40 -> 165131.08 | H43: =H42*H40 -> 163614.12 | I43: =I42*I40 -> 159469.11 | J43: =J42*J40 -> 160621.87 | K43: =K42*K40 -> 159146.33 | ... O43: =O42*O40 -> 140247.97
A44: 5.Чистый дисконтировнный денежный поток нарастающим итогом, руб. | B44: CFD_C | D44: =D43 -> -475111.3 | E44: =D44+E43 -> -836204.69 | F44: =E44+F43 -> -1411273 | G44: =F44+G43 -> -1246141.9 | H44: =G44+H43 -> -1082527.8 | I44: =H44+I43 -> -923058.64 | J44: =I44+J43 -> -762436.77 | K44: =J44+K43 -> -603290.44 | L44: =K44+L43 -> -448175.93 | ... O44: =N44+O43 -> 3108.3712
A45: 6. Дисконтируемые поступления (доходы), связанные с реализацией проекта, руб. | B45: CIFD | C45: =SUM(D45:O45) -> 1838414.6 | D45: =('Е1.1.1 и 1.1.2'!E8+'Е1.1.1 и 1.1.2'!E9)*D42 -> 0 | E45: =('Е1.1.1 и 1.1.2'!F8+'Е1.1.1 и 1.1.2'!F9)*E42 -> 0 | F45: =('Е1.1.1 и 1.1.2'!G8+'Е1.1.1 и 1.1.2'!G9)*F42 -> 0 | G45: =('Е1.1.1 и 1.1.2'!H8+'Е1.1.1 и 1.1.2'!H9)*G42 -> 211889.71 | H45: =('Е1.1.1 и 1.1.2'!I8+'Е1.1.1 и 1.1.2'!I9)*H42 -> 209943.2 | I45: =('Е1.1.1 и 1.1.2'!J8+'Е1.1.1 и 1.1.2'!J9)*I42 -> 208014.57 | J45: =('Е1.1.1 и 1.1.2'!K8+'Е1.1.1 и 1.1.2'!K9)*J42 -> 206103.67 | K45: =('Е1.1.1 и 1.1.2'!L8+'Е1.1.1 и 1.1.2'!L9)*K42 -> 204210.31 | ... O45: =('Е1.1.1 и 1.1.2'!P8+'Е1.1.1 и 1.1.2'!P9)*O42 -> 196809.23
A46: 7. Дисконтируемые эксплуатационные расходы проекта, руб | B46: COFэD | C46: =SUM(D46:O46) -> 424033.3 | D46: =D42*'Е1.1.1 и 1.1.2'!E11 -> 0 | E46: =E42*'Е1.1.1 и 1.1.2'!F11 -> 0 | F46: =F42*'Е1.1.1 и 1.1.2'!G11 -> 0 | G46: =G42*'Е1.1.1 и 1.1.2'!H11 -> 46758.626 | H46: =H42*'Е1.1.1 и 1.1.2'!I11 -> 46329.081 | I46: =I42*'Е1.1.1 и 1.1.2'!J11 -> 48545.464 | J46: =J42*'Е1.1.1 и 1.1.2'!K11 -> 45481.794 | K46: =K42*'Е1.1.1 и 1.1.2'!L11 -> 45063.979 | ... O46: =O42*'Е1.1.1 и 1.1.2'!P11 -> 56561.263
A47: 8. Дисконтируемые инвестиционные расходы проекта, руб | B47: COFиD | C47: =SUM(D47:O47) -> 1411273 | D47: =D42*'В1.1.1'!D7 -> 475111.3 | E47: =E42*'В1.1.1'!E7 -> 361093.39 | F47: =F42*'В1.1.1'!F7 -> 575068.27 | G47: =G42*'В1.1.1'!G7 -> 0 | H47: =H42*'В1.1.1'!H7 -> 0 | I47: =I42*'В1.1.1'!I7 -> 0 | J47: =J42*'В1.1.1'!J7 -> 0 | K47: =K42*'В1.1.1'!K7 -> 0 | ... O47: =O42*'В1.1.1'!O7 -> 0
O49: Таблица Е 1.3.4
A51: Расчет дисконтированных значений чистого денежного потока для ИТ-проекта 2-его типа по месяцам 1-го года жизни решения
P52: для расчетва ВСД
A53: Наименование показателя | B53: Обозна- чение | C53: Всего за 1 год | D53: в т.ч. по периодам (месяцам) 1-го года жизни решения | P53: 2-го года жизни решения | AB53: 3-го года жизни решения | AN53: 4-го года жизни решения | AZ53: 5-го года жизни решения
D54: 1 месяц | E54: 2 месяц | F54: 3 месяц | G54: 4 месяц | H54: 5 месяц | I54: 6 месяц | J54: 7 месяц | K54: 8 месяц | L54: 9 месяц | M54: 10 месяц | N54: 11 месяц | O54: 12 месяц | P54: 1 | Q54: 2 | R54: 3 | S54: 4 | T54: 5 | U54: 6 | V54: 7 | W54: 8 | X54: 9 | Y54: 10 | Z54: 11 | AA54: 12 | AB54: 1 | AC54: 2 | AD54: 3 | AE54: 4 | AF54: 5 | AG54: 6 | AH54: 7 | AI54: 8 | AJ54: 9 | AK54: 10 | AL54: 11 | AM54: 12 | AN54: 1 | AO54: 2 | AP54: 3 | AQ54: 4 | AR54: 5 | AS54: 6 | AT54: 7 | AU54: 8 | AV54: 9 | AW54: 10 | AX54: 11 | AY54: 12 | AZ54: 1 | BA54: 2 | BB54: 3 | BC54: 4 | BD54: 5 | BE54: 6 | BF54: 7 | BG54: 8 | BH54: 9 | BI54: 10 | BJ54: 11 | BK54: 12
A55: 1.Чистый денежный поток, руб. | B55: СF | C55: =SUM(D55:O55) -> 9644389.1 | D55: ='Е1.1.1 и 1.1.2'!E32 -> -475111.3 | E55: ='Е1.1.1 и 1.1.2'!F32 -> -364441.3 | F55: ='Е1.1.1 и 1.1.2'!G32 -> -585781.3 | G55: ='Е1.1.1 и 1.1.2'!H32 -> 1232198.9 | H55: ='Е1.1.1 и 1.1.2'!I32 -> 1232198.9 | I55: ='Е1.1.1 и 1.1.2'!J32 -> 1229432.1 | J55: ='Е1.1.1 и 1.1.2'!K32 -> 1232198.9 | K55: ='Е1.1.1 и 1.1.2'!L32 -> 1232198.9 | ... O55: ='Е1.1.1 и 1.1.2'!P32 -> 1217665.4 | P55: =$E$25/12 -> -39592.608 | Q55: =$E$25/12 -> -39592.608 | R55: =$E$25/12 -> -39592.608 | S55: =$E$25/12 -> -39592.608 | T55: =$E$25/12 -> -39592.608 | U55: =$E$25/12 -> -39592.608 | V55: =$E$25/12 -> -39592.608 | W55: =$E$25/12 -> -39592.608 | ... AA55: =$E$25/12 -> -39592.608 | AB55: =$F$25/12 -> -30370.108 | AC55: =$F$25/12 -> -30370.108 | AD55: =$F$25/12 -> -30370.108 | AE55: =$F$25/12 -> -30370.108 | AF55: =$F$25/12 -> -30370.108 | AG55: =$F$25/12 -> -30370.108 | AH55: =$F$25/12 -> -30370.108 | AI55: =$F$25/12 -> -30370.108 | ... AM55: =$F$25/12 -> -30370.108 | AN55: =$G$25/12 -> 0 | AO55: =$G$25/12 -> 0 | AP55: =$G$25/12 -> 0 | AQ55: =$G$25/12 -> 0 | AR55: =$G$25/12 -> 0 | AS55: =$G$25/12 -> 0 | AT55: =$G$25/12 -> 0 | AU55: =$G$25/12 -> 0 | ... AY55: =$G$25/12 -> 0 | AZ55: =$H$25/12 -> 0 | BA55: =$H$25/12 -> 0 | BB55: =$H$25/12 -> 0 | BC55: =$H$25/12 -> 0 | BD55: =$H$25/12 -> 0 | BE55: =$H$25/12 -> 0 | BF55: =$H$25/12 -> 0 | BG55: =$H$25/12 -> 0 | ... BK55: =$H$25/12 -> 0
A56: 2.Чистый денежный поток нарастающим итогом, руб. | B56: CFC | D56: =D55 -> -475111.3 | E56: =D56+E55 -> -839552.6 | F56: =E56+F55 -> -1425333.9 | G56: =F56+G55 -> -193135.01 | H56: =G56+H55 -> 1039063.9 | I56: =H56+I55 -> 2268496 | J56: =I56+J55 -> 3500694.9 | K56: =J56+K55 -> 4732893.8 | L56: =K56+L55 -> 5962325.9 | ... O56: =N56+O55 -> 9644389.1
A57: 3. Коэффициент дисконтирования, посчитанный по ставке r мес | B57: kD мес | D57: ='Е1.2.1 - 1.2.3'!C30 -> 1 | E57: ='Е1.2.1 - 1.2.3'!D30 -> 0.99081358 | F57: ='Е1.2.1 - 1.2.3'!E30 -> 0.98171155 | G57: ='Е1.2.1 - 1.2.3'!F30 -> 0.97269313 | H57: ='Е1.2.1 - 1.2.3'!G30 -> 0.96375757 | I57: ='Е1.2.1 - 1.2.3'!H30 -> 0.95490408 | J57: ='Е1.2.1 - 1.2.3'!I30 -> 0.94613193 | K57: ='Е1.2.1 - 1.2.3'!J30 -> 0.93744037 | ... O57: ='Е1.2.1 - 1.2.3'!N30 -> 0.90346525
A58: 4.Чистый дисконтированный денежный поток, руб. | B58: CFD | C58: =SUM(D58:O58) -> 8969353.2 | D58: =D57*D55 -> -475111.3 | E58: =E57*E55 -> -361093.39 | F58: =F57*F55 -> -575068.27 | G58: =G57*G55 -> 1198551.4 | H58: =H57*H55 -> 1187541 | I58: =I57*I55 -> 1173989.8 | J58: =J57*J55 -> 1165822.7 | K58: =K57*K55 -> 1155113 | ... O58: =O57*O55 -> 1100118.4
A59: 5.Чистый дисконтировнный денежный поток нарастающим итогом, руб. | B59: CFD_C | D59: =D58 -> -475111.3 | E59: =D59+E58 -> -836204.69 | F59: =E59+F58 -> -1411273 | G59: =F59+G58 -> -212721.56 | H59: =G59+H58 -> 974819.44 | I59: =H59+I58 -> 2148809.2 | J59: =I59+J58 -> 3314631.9 | K59: =J59+K58 -> 4469744.9 | L59: =K59+L58 -> 5611676.7 | ... O59: =N59+O58 -> 8969353.2

Sheet Е1.4.1 - 1.4.4
D1: Таблица Е 1.4.1
A2: Показатели эффективности ИТ-проекта (тип 1)
A4: Наименование показателя | B4: Обозна- чение | C4: Ед.изм. | D4: Величина показателя
A6: 1.Объем инвестиций | B6: I проект | C6: руб. | D6: ='В1.1.1'!C7 -> 1425333.9
A7: 2.Ставка дисконтирования | B7: r | C7: % | D7: ='Е1.2.1 - 1.2.3'!C6 -> 0.11125912
A8: 3.Чистая приведенная стоимость проекта | B8: NPV | C8: руб. | D8: ='Е1.3.1 - Е1.3.4'!C10 -> 3531126
A9: 4.Внутренняя ставка доходности | B9: IRR | C9: % | D9: =IRR('Е1.3.1 - Е1.3.4'!D7:H7) -> #NUM!
A10: 5.Простой срок окупаемости | B10: PPs | C10: лет | D10: =4+(('Е1.3.1 - Е1.3.4'!G8*-1)/'Е1.3.1 - Е1.3.4'!H7) -> #DIV/0!
A11: 6.Дисконтированный срок окупаемости | B11: PPd | C11: лет | D11: =4+(('Е1.3.1 - Е1.3.4'!G11*-1)/'Е1.3.1 - Е1.3.4'!H10) -> #DIV/0!
A12: 7.Индекс доходности инвестиций | B12: PI | C12: индекс | D12: =('Е1.3.1 - Е1.3.4'!C12-'Е1.3.1 - Е1.3.4'!C13)/'Е1.3.1 - Е1.3.4'!C14 -> 3.4774026
A13: 8. Чистая конечная стоимость | B13: NTV | C13: руб. | D13: ='Е1.3.1 - Е1.3.4'!H17 -> 5384861.8
D15: Таблица Е 1.4.2
A16: Показатели эффективности ИТ-проекта (тип 2)
A18: Наименование показателя | B18: Обозна- чение | C18: Ед.изм. | D18: Величина показателя
A20: 1.Объем инвестиций | B20: I проект | C20: руб. | D20: ='В1.1.1'!C7 -> 1425333.9
A21: 2.Ставка дисконтирования | B21: r | C21: % | D21: ='Е1.2.1 - 1.2.3'!C6 -> 0.11125912
A22: 3.Чистая приведенная стоимость проекта | B22: NPV | C22: руб. | D22: ='Е1.3.1 - Е1.3.4'!C28 -> 8921727
A23: 4.Внутренняя ставка доходности | B23: IRR | C23: % | D23: =IRR('Е1.3.1 - Е1.3.4'!D25:H25) -> -0.77942306
A24: 5.Простой срок окупаемости | B24: PPs | C24: лет | D24: =1+('Е1.3.1 - Е1.3.4'!D26*-1/'Е1.3.1 - Е1.3.4'!E25) -> 21.299221
A25: 6.Дисконтированный срок окупаемости | B25: PPd | C25: лет | D25: =1+'Е1.3.1 - Е1.3.4'!D29*-1/'Е1.3.1 - Е1.3.4'!E28 -> 23.557694
A26: 7.Коэффициент удельной эффективности проекта (модифицированный) | B26: PI_мод | C26: коэф-т | D26: =D22/D20 -> 6.2593944
A27: 8. Чистая конечная стоимость | B27: NTV | C27: руб. | D27: ='Е1.3.1 - Е1.3.4'!H32 -> 13605368
D29: Таблица Е 1.4.3
A30: Показатели эффективности ИТ-проекта (тип 1) (помесячно)
A32: Наименование показателя | B32: Обозна- чение | C32: Ед.изм. | D32: Величина показателя
A34: 1.Объем инвестиций | B34: I проект | C34: руб. | D34: ='В1.1.1'!C7 -> 1425333.9
A35: 2.Ставка дисконтирования | B35: r | C35: % | D35: ='Е1.2.1 - 1.2.3'!C19 -> 0.11125912
A36: 3.Чистая приведенная стоимость проекта | B36: NPV | C36: руб. | D36: ='Е1.3.1 - Е1.3.4'!C10 -> 3531126
A37: 4.Внутренняя ставка доходности | B37: IRR | C37: % | D37: =IRR('Е1.3.1 - Е1.3.4'!D40:BK40) -> 0.10312799
A38: 5.Простой срок окупаемости | B38: PPs | C38: месяцев | D38: =9+('Е1.1.1 и 1.1.2'!M13*-1/'Е1.1.1 и 1.1.2'!N12) -> 11.428425
A39: 6.Дисконтированный срок окупаемости | B39: PPd | C39: месяцев | D39: =9+('Е1.3.1 - Е1.3.4'!L44*-1/'Е1.3.1 - Е1.3.4'!M43) -> 11.868587
A40: 7.Индекс доходности инвестиций, PI | B40: PI | C40: индекс | D40: =('Е1.3.1 - Е1.3.4'!C12-'Е1.3.1 - Е1.3.4'!C13)/'Е1.3.1 - Е1.3.4'!C14 -> 3.4774026
A41: 8. Чистая конечная стоимость | B41: NTV | C41: руб. | D41: ='Е1.3.1 - Е1.3.4'!H17 -> 5384861.8
D43: Таблица Е 1.4.4
A44: Показатели эффективности ИТ-проекта (тип 2) (помесячно)
A46: Наименование показателя | B46: Обозна- чение | C46: Ед.изм. | D46: Величина показателя
A48: 1.Объем инвестиций | B48: I проект | C48: руб. | D48: ='В1.1.1'!C7 -> 1425333.9
A49: 2.Ставка дисконтирования | B49: r | C49: % | D49: ='Е1.2.1 - 1.2.3'!C19 -> 0.11125912
A50: 3.Чистая приведенная стоимость проекта | B50: NPV | C50: руб. | D50: ='Е1.3.1 - Е1.3.4'!H29 -> 8921727
A51: 4.Внутренняя ставка доходности | B51: IRR | C51: % | D51: =IRR('Е1.3.1 - Е1.3.4'!D55:BK55) -> 0.53273551
A52: 5.Простой срок окупаемости | B52: PPs | C52: месяцев | D52: =3+('Е1.1.1 и 1.1.2'!G33*-1/'Е1.1.1 и 1.1.2'!H32) -> 4.1567401
A53: 6.Дисконтированный срок окупаемости | B53: PPd | C53: месяцев | D53: =3+('Е1.3.1 - Е1.3.4'!F59*-1/'Е1.3.1 - Е1.3.4'!G58) -> 4.1774822
A54: 7.Коэффициент удельной эффективности проекта (модифицированный) | B54: PI_мод | C54: коэф-т | D54: =D50/D48 -> 6.2593944
A55: 8. Чистая конечная стоимость | B55: NTV | C55: руб. | D55: ='Е1.3.1 - Е1.3.4'!H32 -> 13605368

Sheet Лист1
B1: Отчет о совместимости для Таблицы для расчета_в2.1_ЭТАЛОН.xls
B2: Дата отчета: 23.04.2024 20:24
B4: Если вы сохраните книгу в более старом формате или откроете в более ранней версии Microsoft Excel, приведенные ниже функции будут недоступны.
B6: Несущественная потеря точности | E6: Число экземпляров | F6: Версия
B8: Некоторые ячейки или стили в этой книге содержат форматирование, не поддерживаемое выбранным форматом файла. Эти форматы будут преобразованы в наиболее близкий из имеющихся форматов. | E8: 3 | F8: Excel 97–2003
